Workbook

Sheet README
A1: WENDY 7 - final2 (on hold, not submitted): actuarial assumptions and feature map
A2: This version | B2: Model run 'c5' of R/4_models_iterwendy07.R (models/wendy_iteration_07/c5/). All its changes are baked into the input sheets; sheet Changes_vs_WENDY4 lists each one with its reason and measured effect.
A3: How to run | B3: ASSUMPTIONS_XLSX=docs/assumptions_wendy07_final2.xlsx FINAL_FIT=1 FINAL_METHODS=all RUN_TAG=<tag> Rscript R/4_models_iterwendy07.R (no FEATURE_EDITS / SPEC_EDITS / IBNR_* / BAGS / METHOD_MIX needed). Then R/4_final_wendy07.R blends with SAM 3.
A4: Changes vs WENDY 4 | B4: See sheet Changes_vs_WENDY4. Full reasoning per step: docs/wendy07_experiment_log.md; every try: docs/wendy07_experiment_register.xlsx.
A5: Orange cells | B5: Cells changed from the WENDY 4 workbook (feature codes, Model_Spec, Settings).
A6: Line blend | B6: The submitted prediction is a per-line blend with SAM 3 (sheet SAM3_Blend); this workbook drives the WENDY 7 part.
A7: Submission file | B7: output/submission/submission_20261022_2328_wendy07_final2.csv (MD5 99135ba796a021c92c186e3e7bf71d3f)
A8: Model per peril | B8: Model_Spec: frequency = Poisson GBM (exposure x reported share as volume); severity = Gamma GBM (data-rich perils) or Gamma GLM on few factors (sparse/heavy perils); Tweedie GBM challenger; 'auto' selection keeps the better one per peril on the two validation folds.
A9: --- WENDY 4 notes (still valid unless changed above) ---
A10: Purpose | B10: One place for every target, data and feature decision behind iteration WENDY 4. The R script R/4_models_iterwendy04.R READS this workbook: sheets Features_*, Model_Spec, Structural_Zeros and Settings drive the model. Edit them here, re-run the script, compare scores.
A11: Where to save | B11: docs/assumptions_wendy04.xlsx in the repo (or set env var ASSUMPTIONS_XLSX to another path).
A12: Editable cells | B12: Blue text on yellow fill = inputs the script reads. Everything else is documentation.
A13: Feature codes | B13: In Features_<line>, each peril column holds: F = frequency model only, S = severity model only, B = both, - = not used. A feature is used only if its 'use' cell is Y.
A14: decision column | B14: Include = actuarial rationale, kept. Test = plausible but unproven, kept only if validation supports it (set use = N to drop). Exclude = no mechanism, noise, leakage, circular or duplicate.
A15: mono_freq / mono_sev | B15: Monotone constraint for numeric/boolean features: 1 = can only increase, -1 = can only decrease, 0 = free. Ignored for text categories.
A16: Model per peril | B16: Model_Spec: frequency = Poisson GBM (exposure x reported share as volume); severity = Gamma GBM (data-rich perils) or Gamma GLM on few factors (sparse/heavy perils); Tweedie GBM challenger; 'auto' selection keeps the better one per peril on the two validation folds.
A17: Validation | B17: Two out-of-time folds: fit 2021-22 -> score 2023, fit 2021-23 -> score 2024. Actuals are DEVELOPED (divided by the row's reported share) so models that predict ultimate cost are not penalised - this fixes the WENDY 3 scoring bias.
A18: Example row | B18: Features_Motor row 'ncb_years': decision Include, use Y, mono_freq -1, codes F F F - - (frequency of own damage, third-party property, bodily injury).
A19: Changes vs WENDY 3 | B19: 1) Frequency x severity per peril instead of one Tweedie per peril; 2) IBNR as a frequency offset, not a target uplift; 3) severity trend to the prediction year; 4) outlier claim limit before capping; 5) per-peril feature lists (noise, marketing and circular columns removed); 6) structural zeros (cover not bought -> 0); 7) prior-year claims history features known at renewal; 8) expected recoveries on open motor own-damage/theft; 9) developed-actual validation on 2 folds.
A20: Verification status | B20: Numbers quoted in Target_Assumptions come from the Oct 2026 profiling and the WENDY 3 model card. Treat them as approximate and re-check against the cleaning report after the next run.

Sheet Summary
A1: line | B1: peril | C1: freq features used | D1: sev features used | E1: sev_model | F1: cap_quantile | G1: rationale
A2: motor | B2: own_damage | C2: =COUNTIFS(Features_Motor!$G:$G,"Y",Features_Motor!J:J,"F")+COUNTIFS(Features_Motor!$G:$G,"Y",Features_Motor!J:J,"B") -> 38 | D2: =COUNTIFS(Features_Motor!$G:$G,"Y",Features_Motor!J:J,"S")+COUNTIFS(Features_Motor!$G:$G,"Y",Features_Motor!J:J,"B") -> 11 | E2: =Model_Spec!D2 -> gamma_gbm | F2: =Model_Spec!F2 -> 0.999 | G2: =Model_Spec!Q2 -> ~49k claims: data-rich, GBM for both parts.
A3: motor | B3: third_party_prop | C3: =COUNTIFS(Features_Motor!$G:$G,"Y",Features_Motor!K:K,"F")+COUNTIFS(Features_Motor!$G:$G,"Y",Features_Motor!K:K,"B") -> 33 | D3: =COUNTIFS(Features_Motor!$G:$G,"Y",Features_Motor!K:K,"S")+COUNTIFS(Features_Motor!$G:$G,"Y",Features_Motor!K:K,"B") -> 5 | E3: =Model_Spec!D3 -> gamma_gbm | F3: =Model_Spec!F3 -> 0.999 | G3: =Model_Spec!Q3 -> ~34k claims: data-rich.
A4: motor | B4: bodily_injury | C4: =COUNTIFS(Features_Motor!$G:$G,"Y",Features_Motor!L:L,"F")+COUNTIFS(Features_Motor!$G:$G,"Y",Features_Motor!L:L,"B") -> 17 | D4: =COUNTIFS(Features_Motor!$G:$G,"Y",Features_Motor!L:L,"S")+COUNTIFS(Features_Motor!$G:$G,"Y",Features_Motor!L:L,"B") -> 4 | E4: =Model_Spec!D4 -> gamma_glm | F4: =Model_Spec!F4 -> 0.995 | G4: =Model_Spec!Q4 -> ~7.6k claims, long tail (median report lag ~127 days), 2024 immature: Poisson GBM frequency + Gamma GLM severity on few factors; latest year left out of severity fit.
A5: motor | B5: theft | C5: =COUNTIFS(Features_Motor!$G:$G,"Y",Features_Motor!M:M,"F")+COUNTIFS(Features_Motor!$G:$G,"Y",Features_Motor!M:M,"B") -> 21 | D5: =COUNTIFS(Features_Motor!$G:$G,"Y",Features_Motor!M:M,"S")+COUNTIFS(Features_Motor!$G:$G,"Y",Features_Motor!M:M,"B") -> 9 | E5: =Model_Spec!D5 -> gamma_gbm | F5: =Model_Spec!F5 -> 0.999 | G5: =Model_Spec!Q5 -> ~6.5k claims; recoveries matter.
A6: motor | B6: glass_hail | C6: =COUNTIFS(Features_Motor!$G:$G,"Y",Features_Motor!N:N,"F")+COUNTIFS(Features_Motor!$G:$G,"Y",Features_Motor!N:N,"B") -> 16 | D6: =COUNTIFS(Features_Motor!$G:$G,"Y",Features_Motor!N:N,"S")+COUNTIFS(Features_Motor!$G:$G,"Y",Features_Motor!N:N,"B") -> 9 | E6: =Model_Spec!D6 -> gamma_gbm | F6: =Model_Spec!F6 -> 0.999 | G6: =Model_Spec!Q6 -> Weather-driven: no frequency trend.
A7: buildings | B7: storm | C7: =COUNTIFS(Features_Buildings!$G:$G,"Y",Features_Buildings!J:J,"F")+COUNTIFS(Features_Buildings!$G:$G,"Y",Features_Buildings!J:J,"B") -> 17 | D7: =COUNTIFS(Features_Buildings!$G:$G,"Y",Features_Buildings!J:J,"S")+COUNTIFS(Features_Buildings!$G:$G,"Y",Features_Buildings!J:J,"B") -> 11 | E7: =Model_Spec!D7 -> gamma_gbm | F7: =Model_Spec!F7 -> 0.999 | G7: =Model_Spec!Q7 -> ~7.8k claims; weather-driven.
A8: buildings | B8: flood | C8: =COUNTIFS(Features_Buildings!$G:$G,"Y",Features_Buildings!K:K,"F")+COUNTIFS(Features_Buildings!$G:$G,"Y",Features_Buildings!K:K,"B") -> 12 | D8: =COUNTIFS(Features_Buildings!$G:$G,"Y",Features_Buildings!K:K,"S")+COUNTIFS(Features_Buildings!$G:$G,"Y",Features_Buildings!K:K,"B") -> 10 | E8: =Model_Spec!D8 -> gamma_glm | F8: =Model_Spec!F8 -> 0.995 | G8: =Model_Spec!Q8 -> ~2.2k claims, strong hazard structure: GBM frequency, GLM severity.
A9: buildings | B9: escape_of_water | C9: =COUNTIFS(Features_Buildings!$G:$G,"Y",Features_Buildings!L:L,"F")+COUNTIFS(Features_Buildings!$G:$G,"Y",Features_Buildings!L:L,"B") -> 28 | D9: =COUNTIFS(Features_Buildings!$G:$G,"Y",Features_Buildings!L:L,"S")+COUNTIFS(Features_Buildings!$G:$G,"Y",Features_Buildings!L:L,"B") -> 10 | E9: =Model_Spec!D9 -> gamma_gbm | F9: =Model_Spec!F9 -> 0.999 | G9: =Model_Spec!Q9 -> ~10k claims: data-rich.
A10: buildings | B10: subsidence | C10: =COUNTIFS(Features_Buildings!$G:$G,"Y",Features_Buildings!M:M,"F")+COUNTIFS(Features_Buildings!$G:$G,"Y",Features_Buildings!M:M,"B") -> 14 | D10: =COUNTIFS(Features_Buildings!$G:$G,"Y",Features_Buildings!M:M,"S")+COUNTIFS(Features_Buildings!$G:$G,"Y",Features_Buildings!M:M,"B") -> 11 | E10: =Model_Spec!D10 -> gamma_glm | F10: =Model_Spec!F10 -> 0.995 | G10: =Model_Spec!Q10 -> ~1.3k claims, long tail (median lag ~94 days): GLM severity, latest year excluded from severity.
A11: buildings | B11: fire | C11: =COUNTIFS(Features_Buildings!$G:$G,"Y",Features_Buildings!N:N,"F")+COUNTIFS(Features_Buildings!$G:$G,"Y",Features_Buildings!N:N,"B") -> 19 | D11: =COUNTIFS(Features_Buildings!$G:$G,"Y",Features_Buildings!N:N,"S")+COUNTIFS(Features_Buildings!$G:$G,"Y",Features_Buildings!N:N,"B") -> 9 | E11: =Model_Spec!D11 -> gamma_glm | F11: =Model_Spec!F11 -> 0.99 | G11: =Model_Spec!Q11 -> ~1.1k claims, very heavy severity: GLM severity, lower cap.
A12: buildings | B12: accidental_damage | C12: =COUNTIFS(Features_Buildings!$G:$G,"Y",Features_Buildings!O:O,"F")+COUNTIFS(Features_Buildings!$G:$G,"Y",Features_Buildings!O:O,"B") -> 21 | D12: =COUNTIFS(Features_Buildings!$G:$G,"Y",Features_Buildings!O:O,"S")+COUNTIFS(Features_Buildings!$G:$G,"Y",Features_Buildings!O:O,"B") -> 5 | E12: =Model_Spec!D12 -> gamma_gbm | F12: =Model_Spec!F12 -> 0.999 | G12: =Model_Spec!Q12 -> ~3.8k claims; structural zero without AD cover.
A13: contents | B13: theft | C13: =COUNTIFS(Features_Contents!$G:$G,"Y",Features_Contents!J:J,"F")+COUNTIFS(Features_Contents!$G:$G,"Y",Features_Contents!J:J,"B") -> 25 | D13: =COUNTIFS(Features_Contents!$G:$G,"Y",Features_Contents!J:J,"S")+COUNTIFS(Features_Contents!$G:$G,"Y",Features_Contents!J:J,"B") -> 9 | E13: =Model_Spec!D13 -> gamma_gbm | F13: =Model_Spec!F13 -> 0.999 | G13: =Model_Spec!Q13 -> ~7.9k claims.
A14: contents | B14: escape_of_water | C14: =COUNTIFS(Features_Contents!$G:$G,"Y",Features_Contents!K:K,"F")+COUNTIFS(Features_Contents!$G:$G,"Y",Features_Contents!K:K,"B") -> 19 | D14: =COUNTIFS(Features_Contents!$G:$G,"Y",Features_Contents!K:K,"S")+COUNTIFS(Features_Contents!$G:$G,"Y",Features_Contents!K:K,"B") -> 8 | E14: =Model_Spec!D14 -> gamma_gbm | F14: =Model_Spec!F14 -> 0.999 | G14: =Model_Spec!Q14 -> ~5.4k claims.
A15: contents | B15: accidental_damage | C15: =COUNTIFS(Features_Contents!$G:$G,"Y",Features_Contents!L:L,"F")+COUNTIFS(Features_Contents!$G:$G,"Y",Features_Contents!L:L,"B") -> 21 | D15: =COUNTIFS(Features_Contents!$G:$G,"Y",Features_Contents!L:L,"S")+COUNTIFS(Features_Contents!$G:$G,"Y",Features_Contents!L:L,"B") -> 7 | E15: =Model_Spec!D15 -> gamma_gbm | F15: =Model_Spec!F15 -> 0.999 | G15: =Model_Spec!Q15 -> ~9.2k claims; structural zero without AD cover.
A16: contents | B16: flood | C16: =COUNTIFS(Features_Contents!$G:$G,"Y",Features_Contents!M:M,"F")+COUNTIFS(Features_Contents!$G:$G,"Y",Features_Contents!M:M,"B") -> 13 | D16: =COUNTIFS(Features_Contents!$G:$G,"Y",Features_Contents!M:M,"S")+COUNTIFS(Features_Contents!$G:$G,"Y",Features_Contents!M:M,"B") -> 10 | E16: =Model_Spec!D16 -> gamma_glm | F16: =Model_Spec!F16 -> 0.995 | G16: =Model_Spec!Q16 -> ~1.6k claims: GLM severity.
A18: Counts update when you change 'use' or peril codes in the Features sheets.

Sheet Target_Assumptions
A1: id | B1: topic | C1: question | D1: decision | E1: treatment in script | F1: evidence | G1: if done differently | H1: status
A2: 1 | B2: Recoveries | C2: Should recoveries be taken out? | D2: YES - keep deducting. The target is defined net of recoveries. | E2: claim cost = incurred_to_date - recoveries (as 2_clean). Open motor own_damage/theft claims have no recoveries booked yet, so expected recoveries are deducted: incurred x (closed recoveries / closed incurred) for that peril (setting open_claim_recovery_adjust). | F2: Recoveries appear only on CLOSED motor own_damage (~28.6% of claims) and theft (~12.0%); closed recoveries ~27.7M vs closed paid ~656.9M. | G2: Ignoring recoveries overstates motor cost; ignoring the open-claim gap overstates the immature 2024 year. | H2: Decided
A3: 2 | B3: Open claims | C3: Should claims that are not closed be taken out? | D3: NO - keep them at incurred (paid + case reserve). | E3: Open claims count in frequency and severity at incurred_to_date. | F3: Share open by loss year: 2021 0.9%, 2022 1.5%, 2023 3.2%, 2024 20.2%. Large/complex claims (bodily injury, subsidence) stay open longest. | G3: Dropping open claims removes ~20% of 2024 claims and is biased towards the largest ones -> severe under-prediction. | H3: Decided
A4: 3 | B4: Case development (IBNER) | C4: Will open case reserves move? | D4: Assume case reserves are adequate on average. | E4: No IBNER factor. Long-tail perils (bodily injury, subsidence) exclude the latest training year from the SEVERITY fit (Model_Spec sev_exclude_recent_years) so immature small claims do not bias severity down. | F4: Only one valuation date (31 Dec 2024) - development cannot be measured. | G4: Applying an untested factor adds error. | H4: Assumption - verify
A5: 4 | B5: Late reporting (IBNR) | C5: How to treat claims not yet reported? | D5: Model ULTIMATE frequency. | E5: Per peril, reported share = ECDF of report lags (2021-22 losses) at (31 Dec 2024 - row mid-date). Frequency volume = exposure x reported share. Validation actuals divided by the same share. | F5: 2024 IBNR count factor ~1.76 bodily injury, ~1.50 subsidence, ~1.02-1.06 others (WENDY 3). | G5: WENDY 3 multiplied targets by the factor -> scored against reported actuals -> unfair penalty. | H5: Decided
A6: 5 | B6: Repudiated claims | C6: Include declined claims? | D6: NO - excluded (cost 0, not counted). | E6: counts == TRUE only. | F6: ~1.0-1.1% of claims each year. | G6: - | H6: Decided
A7: 6 | B7: Excess | C7: Deduct the excess? | D7: NO - paid/incurred are already net of excess. | E7: Excess kept as a feature only. | F7: Data dictionary: paid_to_date is net of excess. | G7: Deducting again double-counts. | H7: Decided
A8: 7 | B8: Nil claims | C8: Non-repudiated claims with zero net cost? | D8: Excluded from frequency and severity. | E8: Frequency counts claims with net cost > 0, severity fitted on the same claims, so freq x sev = expected cost. | F8: Claims closed below the excess. | G8: Counting them in frequency but not severity overstates cost. | H8: Decided
A9: 8 | B9: Outlier claim | C9: The 11.9M open bodily-injury claim? | D9: Limit any single claim to 2,000,000 before capping (setting outlier_claim_limit). | E9: pmin(cost, limit). | F9: Paid ~0.74M; next largest claim ~1.12M closed. One claim = ~3.4% of all motor cost. | G9: Kept in full it adds ~7% to every bodily-injury prediction via the cap loading. | H9: Assumption - verify
A10: 9 | B10: Large-loss cap | C10: How to treat the tail? | D10: Cap each claim at a per-peril quantile; spread the excess as a loading. | E10: Model_Spec cap_quantile (0.99-0.999). Loading = trended total / trended capped total. | F10: Heavy tails: fire, flood, subsidence, bodily injury. | G10: Uncapped Gamma/Tweedie fits chase a few claims. | H10: Decided
A11: 10 | B11: Severity inflation | C11: Project severity to 2025? | D11: YES - log-linear trend per peril, clamped. | E11: Trend fitted on capped claim severity by loss year (excluding long-tail immature years); each claim trended to the prediction year (validation year or 2025). Clamp in Settings. | F11: Buildings severity ~8.7k (2021) -> ~10.3k (2024); contents ~2.7k -> ~2.9k. | G11: Without trend, 2025 is priced at the 2022-23 average. | H11: Decided
A12: 11 | B12: Frequency trend | C12: Project frequency? | D12: Only motor non-weather perils, residual-based, clamped. | E12: Model_Spec freq_trend = estimate: log(actual/expected) by year regressed on year after the GBM, so mix change is not counted as trend. | F12: Motor raw frequency 0.146 -> 0.140 (2021-23); weather perils vary with the year's weather, which is already a feature. | G12: Extrapolating weather years is noise. | H12: Assumption - verify
A13: 12 | B13: Unmatched claims | C13: Claims outside any policy row? | D13: Excluded. | E13: Rows with NA row_id dropped (2_clean). | F13: 414 claims; 252 dated exactly 2020-12-01 (placeholder). | G13: - | H13: Decided
... A25: 24 | B25: Validation | C25: How to compare models? | D25: 2 out-of-time folds against developed actuals; Tweedie D2 p = 1.5 (Kaggle metric). | E25: Selection per peril by mean D2 across folds (Settings model_selection = auto). | F25: WENDY 3 used one fold vs reported actuals. | G25: - | H25: Decided

Sheet Features_Motor
A1: column | B1: source | C1: type | D1: description | E1: actuarial_role | F1: decision | G1: use | H1: mono_freq | I1: mono_sev | J1: own_damage | K1: third_party_prop | L1: bodily_injury | M1: theft | N1: glass_hail | O1: reason | P1: guardrail
A2: driver_age | B2: policies_motor | C2: num | D2: Main driver age at row start | E2: Driver risk | F2: Include | G2: Y | H2: 0 | I2: 0 | J2: B | K2: B | L2: B | M2: F | N2: - | O2: Core driver risk; also drives BI severity (vulnerability of occupants)
A3: years_licensed | B3: policies_motor | C3: num | D3: Years main driver licensed (capped at age-16) | E3: Driver experience | F3: Include | G3: Y | H3: 0 | I3: 0 | J3: F | K3: F | L3: F | M3: - | N3: - | O3: Driving experience separate from age
A4: ncb_years | B4: policies_motor | C4: num | D4: No-claims bonus years | E4: Claims history / experience | F4: Include | G4: Y | H4: -1 | I4: 0 | J4: F | K4: F | L4: F | M4: - | N4: - | O4: Strong frequency signal for at-fault perils; theft/glass are not at-fault
A5: vehicle_value_group | B5: policies_motor | C5: num | D5: Vehicle value band 1-20 | E5: Exposure to damage / theft severity | F5: Include | G5: Y | H5: 0 | I5: 1 | J5: B | K5: - | L5: - | M5: B | N5: B | O5: Damage, theft and glass cost scale with value; irrelevant to third-party liability
A6: vehicle_age | B6: policies_motor | C6: num | D6: Vehicle age | E6: Repair cost, theft attractiveness | F6: Include | G6: Y | H6: 0 | I6: 0 | J6: B | K6: F | L6: - | M6: B | N6: S | O6: Repair cost and theft target; glass cost
A7: make_model | B7: policies_motor | C7: cat | D7: Anonymised make/model code (high cardinality) | E7: Vehicle repair cost / theft target | F7: Test | G7: Y | H7: 0 | I7: 0 | J7: B | K7: F | L7: - | M7: B | N7: B | O7: Strong but high-cardinality; dropped for BI (spurious in WENDY 3) | P7: High cardinality - encoded by training rate order; overfit risk on sparse perils
A8: engine_size_cc | B8: policies_motor | C8: num | D8: Engine size | E8: Performance / driving style | F8: Include | G8: Y | H8: 0 | I8: 0 | J8: F | K8: B | L8: F | M8: F | N8: - | O8: Performance proxy
A9: body_type | B9: policies_motor | C9: cat | D9: Body type | E9: Repair cost, use pattern | F9: Include | G9: Y | H9: 0 | I9: 0 | J9: B | K9: B | L9: - | M9: F | N9: S | O9: Repair cost and use pattern
A10: transmission | B10: policies_motor | C10: cat | D10: Manual / automatic | E10: Weak driving-style proxy | F10: Test | G10: Y | H10: 0 | I10: 0 | J10: F | K10: - | L10: - | M10: - | N10: - | O10: Weak; own damage only
A11: seats | B11: policies_motor | C11: num | D11: Seats | E11: Occupants exposed to injury | F11: Test | G11: Y | H11: 0 | I11: 0 | J11: - | K11: - | L11: S | M11: - | N11: - | O11: More occupants -> larger BI claims
A12: vehicle_colour | B12: policies_motor | C12: cat | D12: Colour (~12.5% each, uniform) | E12: None - noise | F12: Exclude | G12: N | H12: 0 | I12: 0 | J12: - | K12: - | L12: - | M12: - | N12: - | O12: Uniform ~12.5% each; no causal path | P12: No causal path; uniform distribution suggests synthetic noise
A13: fuel_type | B13: policies_motor | C13: cat | D13: Petrol/diesel/hybrid/electric | E13: EV repair cost, theft target | F13: Test | G13: Y | H13: 0 | I13: 0 | J13: S | K13: - | L13: - | M13: F | N13: - | O13: EV/hybrid repair cost; theft targeting
A14: driver_assist | B14: policies_motor | C14: cat/bool | D14: Driver-assistance tech | E14: Collision avoidance | F14: Include | G14: Y | H14: 0 | I14: 0 | J14: F | K14: F | L14: F | M14: - | N14: - | O14: Collision avoidance reduces at-fault frequency
A15: cover_type | B15: policies_motor | C15: cat | D15: comprehensive / TPFT / TPO | E15: Defines which perils are covered (structural) | F15: Include | G15: Y | H15: 0 | I15: 0 | J15: B | K15: F | L15: F | M15: B | N15: B | O15: Defines cover; structural zeros applied for perils not covered | P15: Structural zeros enforced - see Structural_Zeros
A16: annual_mileage | B16: policies_motor | C16: num | D16: Declared mileage | E16: Exposure to road risk | F16: Include | G16: Y | H16: 1 | I16: 0 | J16: F | K16: F | L16: F | M16: - | N16: F | O16: Road exposure; more mileage -> more chips
A17: overnight_parking | B17: policies_motor | C17: cat | D17: Garage / driveway / street | E17: Theft, hail, vandalism | F17: Include | G17: Y | H17: 0 | I17: 0 | J17: F | K17: - | L17: - | M17: B | N17: F | O17: Theft and hail protection
A18: vehicle_use | B18: policies_motor | C18: cat | D18: Social / commuting / business | E18: Road exposure | F18: Include | G18: Y | H18: 0 | I18: 0 | J18: F | K18: F | L18: F | M18: - | N18: - | O18: Road exposure
A19: named_young_driver | B19: policies_motor | C19: bool | D19: Under-25 named driver | E19: Driver risk | F19: Include | G19: Y | H19: 1 | I19: 0 | J19: F | K19: F | L19: F | M19: - | N19: - | O19: Young driver risk
A20: telematics_opt_in | B20: policies_motor | C20: bool | D20: Telematics opt-in | E20: Self-selection signal | F20: Test | G20: Y | H20: 0 | I20: 0 | J20: F | K20: F | L20: F | M20: - | N20: - | O20: Self-selection of careful drivers
A21: telematics_score | B21: policies_motor | C21: num | D21: Score 1-100, NA if not opted in | E21: Observed driving behaviour | F21: Test | G21: Y | H21: 0 | I21: 0 | J21: F | K21: F | L21: F | M21: - | N21: - | O21: Observed behaviour; NA if not opted in (direction of scale not documented, so no constraint) | P21: NA by design; GBM handles NA natively
A22: voluntary_excess | B22: all policy files | C22: num | D22: Customer-chosen excess 0/250/500/1000 | E22: Removes small claims; self-selection | F22: Include | G22: Y | H22: -1 | I22: 0 | J22: B | K22: B | L22: B | M22: B | N22: B | O22: Removes small own-damage/theft/glass claims; BI not subject to excess (assumed) | P22: Claims already net of excess - do not subtract again
A23: compulsory_excess | B23: all policy files | C23: num | D23: Insurer-set excess | E23: Removes small claims | F23: Include | G23: Y | H23: 0 | I23: 0 | J23: B | K23: - | L23: - | M23: B | N23: B | O23: Same mechanism as voluntary excess
A24: channel | B24: all policy files | C24: cat | D24: direct / comparison / broker | E24: Selection effect | F24: Test | G24: Y | H24: 0 | I24: 0 | J24: F | K24: F | L24: - | M24: - | N24: - | O24: Selection effect by channel
A25: payment_method | B25: all policy files | C25: cat | D25: annual / monthly | E25: Financial-stress proxy | F25: Test | G25: Y | H25: 0 | I25: 0 | J25: F | K25: F | L25: - | M25: F | N25: - | O25: Financial-stress proxy | P25: Proxy factor - document in guardrails
A26: missed_payments_12m | B26: all policy files | C26: num | D26: Missed payments last 12m | E26: Financial-stress proxy | F26: Test | G26: Y | H26: 1 | I26: 0 | J26: F | K26: F | L26: - | M26: F | N26: - | O26: Financial-stress proxy | P26: Proxy factor - document in guardrails
A27: new_business | B27: all policy files | C27: bool | D27: First year with insurer | E27: Selection / unknown risk | F27: Test | G27: Y | H27: 0 | I27: 0 | J27: F | K27: F | L27: - | M27: - | N27: - | O27: New customers have unknown/higher risk
A28: renewal_count | B28: all policy files | C28: num | D28: Previous renewals | E28: Tenure / survivorship | F28: Test | G28: Y | H28: 0 | I28: 0 | J28: F | K28: F | L28: - | M28: - | N28: - | O28: Tenure; survivorship | P28: Survivorship bias: lapsed customers absent from test
A29: days_quote_to_inception | B29: all policy files | C29: num | D29: Days quote to start | E29: Anti-selection (last-minute buyers) | F29: Test | G29: Y | H29: 0 | I29: 0 | J29: F | K29: F | L29: - | M29: - | N29: - | O29: Last-minute buyers anti-selection
A30: discount_applied | B30: all policy files | C30: num | D30: Discount on price | E30: Commercial decision, not risk | F30: Exclude | G30: N | H30: 0 | I30: 0 | J30: - | K30: - | L30: - | M30: - | N30: - | O30: Commercial pricing decision, not risk | P30: Pricing decision - circular
A31: written_premium | B31: all policy files | C31: num | D31: Premium under current pricing | E31: Current price = old risk model + loadings | F31: Exclude | G31: N | H31: 0 | I31: 0 | J31: - | K31: - | L31: - | M31: - | N31: - | O31: Circular (current price); top gain in WENDY 3. Flip use to Y only as a documented challenger | P31: Circular for a technical price review; also embeds expense/profit loadings
A32: occupation | B32: customers | C32: cat | D32: Occupation | E32: Lifestyle / use | F32: Test | G32: Y | H32: 0 | I32: 0 | J32: F | K32: F | L32: - | M32: - | N32: - | O32: Lifestyle/use; guardrail review | P32: Potential proxy for protected traits - guardrail
A33: marital_status | B33: customers | C33: cat | D33: Marital status | E33: Driving behaviour proxy | F33: Test | G33: Y | H33: 0 | I33: 0 | J33: F | K33: F | L33: - | M33: - | N33: - | O33: Behaviour proxy; guardrail review | P33: Sensitive in some markets - guardrail
A34: household_size | B34: customers | C34: num | D34: People in household | E34: Occupancy, AD, EoW usage | F34: Exclude | G34: N | H34: 0 | I34: 0 | J34: - | K34: - | L34: - | M34: - | N34: - | O34: No clear motor mechanism
A35: credit_band | B35: customers | C35: cat | D35: Credit band A-E | E35: Financial-stress / claims propensity | F35: Test | G35: Y | H35: 0 | I35: 0 | J35: F | K35: F | L35: - | M35: F | N35: - | O35: Claims propensity; regulatory guardrail | P35: Credit-based insurance scoring restricted in some markets - guardrail
A36: prior_claims_5y | B36: customers | C36: num | D36: Declared claims 5y before joining | E36: Claims history | F36: Include | G36: Y | H36: 1 | I36: 0 | J36: F | K36: F | L36: F | M36: F | N36: F | O36: Declared history
A37: licence_points | B37: customers | C37: num | D37: Driving penalty points | E37: Driver conduct | F37: Include | G37: Y | H37: 1 | I37: 0 | J37: F | K37: F | L37: F | M37: - | N37: - | O37: Driver conduct
A38: years_at_address | B38: customers | C38: num | D38: Years at address | E38: Stability | F38: Test | G38: Y | H38: 0 | I38: 0 | J38: F | K38: - | L38: - | M38: F | N38: - | O38: Stability
A39: customer_since_year | B39: customers | C39: num | D39: First policy year | E39: Calendar cohort | F39: Exclude | G39: N | H39: 0 | I39: 0 | J39: - | K39: - | L39: - | M39: - | N39: - | O39: Cohort year; duplicates renewal_count | P39: Duplicates renewal_count; cohort year drifts out of range for 2025
A40: email_domain | B40: customers | C40: cat | D40: Anonymised email domain (~20% each) | E40: None - noise | F40: Exclude | G40: N | H40: 0 | I40: 0 | J40: - | K40: - | L40: - | M40: - | N40: - | O40: Noise | P40: Uniform; no causal path
A41: marketing_consent | B41: customers | C41: bool | D41: Marketing consent | E41: None | F41: Exclude | G41: N | H41: 0 | I41: 0 | J41: - | K41: - | L41: - | M41: - | N41: - | O41: No causal path | P41: No causal path
A42: document_preference | B42: customers | C42: cat | D42: email / post / app | E42: None (age proxy at best) | F42: Exclude | G42: N | H42: 0 | I42: 0 | J42: - | K42: - | L42: - | M42: - | N42: - | O42: No causal path | P42: Proxy only
A43: previous_insurer | B43: customers | C43: cat | D43: Previous insurer | E43: Weak selection signal | F43: Exclude | G43: N | H43: 0 | I43: 0 | J43: - | K43: - | L43: - | M43: - | N43: - | O43: Spurious signal in sparse perils; no clear mechanism | P43: Showed spurious top-10 importance for fire / subsidence in WENDY 3
A44: campaign_code | B44: customers | C44: cat | D44: Acquisition campaign | E44: Marketing | F44: Exclude | G44: N | H44: 0 | I44: 0 | J44: - | K44: - | L44: - | M44: - | N44: - | O44: Marketing | P44: No causal path; null = no campaign
A45: branch_id | B45: customers | C45: cat | D45: Servicing branch | E45: Geography proxy (region already used) | F45: Exclude | G45: N | H45: 0 | I45: 0 | J45: - | K45: - | L45: - | M45: - | N45: - | O45: Duplicates geography | P45: Duplicates geography
A46: marketing_segment | B46: customers | C46: cat | D46: Marketing segment | E46: Opaque derived score | F46: Exclude | G46: N | H46: 0 | I46: 0 | J46: - | K46: - | L46: - | M46: - | N46: - | O46: Opaque derived score | P46: Unknown construction - could encode price or protected traits
A47: region | B47: addresses | C47: cat | D47: Region R01-R12 | E47: Geography | F47: Include | G47: Y | H47: 0 | I47: 0 | J47: B | K47: B | L47: B | M47: B | N47: B | O47: Geography: repair costs, claims culture, crime
A48: urban_density | B48: addresses | C48: cat | D48: rural ... dense_urban | E48: Traffic, crime density | F48: Include | G48: Y | H48: 0 | I48: 0 | J48: B | K48: B | L48: B | M48: B | N48: F | O48: Traffic density and theft; rural crashes are faster (BI severity)
A49: flood_zone | B49: addresses | C49: num | D49: Flood zone 1-5 | E49: Flood hazard | F49: Exclude | G49: N | H49: 0 | I49: 0 | J49: - | K49: - | L49: - | M49: - | N49: - | O49: Home hazard; no motor flood peril
A50: distance_to_river_km | B50: addresses | C50: num | D50: Distance to river | E50: Flood hazard | F50: Exclude | G50: N | H50: 0 | I50: 0 | J50: - | K50: - | L50: - | M50: - | N50: - | O50: Home hazard
A51: elevation_m | B51: addresses | C51: num | D51: Height above river level | E51: Flood hazard | F51: Exclude | G51: N | H51: 0 | I51: 0 | J51: - | K51: - | L51: - | M51: - | N51: - | O51: Home hazard
A52: soil_type | B52: addresses | C52: cat | D52: clay/sand/loam/chalk/rock | E52: Subsidence hazard (clay shrink-swell) | F52: Exclude | G52: N | H52: 0 | I52: 0 | J52: - | K52: - | L52: - | M52: - | N52: - | O52: Home hazard
A53: year_built | B53: addresses | C53: num | D53: Year built | E53: Plumbing age, construction standard | F53: Exclude | G53: N | H53: 0 | I53: 0 | J53: - | K53: - | L53: - | M53: - | N53: - | O53: Home attribute
A54: property_type | B54: addresses | C54: cat | D54: detached/semi/terraced/flat | E54: Exposure, flood floor level | F54: Exclude | G54: N | H54: 0 | I54: 0 | J54: - | K54: - | L54: - | M54: - | N54: - | O54: Home attribute
A55: roof_type | B55: addresses | C55: cat | D55: pitched / flat | E55: Storm and water ingress | F55: Exclude | G55: N | H55: 0 | I55: 0 | J55: - | K55: - | L55: - | M55: - | N55: - | O55: Home attribute
A56: basement | B56: addresses | C56: bool | D56: Basement | E56: Flood / EoW / subsidence | F56: Exclude | G56: N | H56: 0 | I56: 0 | J56: - | K56: - | L56: - | M56: - | N56: - | O56: Home attribute
A57: trees_within_5m | B57: addresses | C57: bool | D57: Trees within 5m | E57: Subsidence (root shrinkage), storm debris | F57: Exclude | G57: N | H57: 0 | I57: 0 | J57: - | K57: - | L57: - | M57: - | N57: - | O57: Home attribute
A58: listed_building | B58: addresses | C58: bool | D58: Listed building | E58: Rebuild cost (severity) | F58: Exclude | G58: N | H58: 0 | I58: 0 | J58: - | K58: - | L58: - | M58: - | N58: - | O58: Home attribute
A59: bedrooms | B59: addresses | C59: num | D59: Bedrooms | E59: Size / severity | F59: Exclude | G59: N | H59: 0 | I59: 0 | J59: - | K59: - | L59: - | M59: - | N59: - | O59: Home attribute
A60: energy_rating | B60: addresses | C60: cat | D60: Energy rating A-G | E60: Building age / heating proxy | F60: Exclude | G60: N | H60: 0 | I60: 0 | J60: - | K60: - | L60: - | M60: - | N60: - | O60: Home attribute | P60: Proxy - keep only where it validates
A61: solar_panels | B61: addresses | C61: bool | D61: Solar panels | E61: Electrical fire, roof damage | F61: Exclude | G61: N | H61: 0 | I61: 0 | J61: - | K61: - | L61: - | M61: - | N61: - | O61: Home attribute
A62: hail_days | B62: weather (policy year) | C62: num | D62: Hail days in year | E62: Hail hazard | F62: Include | G62: Y | H62: 1 | I62: 0 | J62: - | K62: - | L62: - | M62: - | N62: B | O62: Hail damage to glass/bodywork | P62: Realised weather of the row's year (2025 supplied for test)
A63: wind_exposure_index | B63: weather (policy year) | C63: num | D63: Wind exposure 0-10 | E63: Storm hazard | F63: Test | G63: Y | H63: 0 | I63: 0 | J63: - | K63: - | L63: - | M63: - | N63: F | O63: Debris chips | P63: Realised weather
A64: freezing_days | B64: weather (policy year) | C64: num | D64: Days below freezing | E64: Burst pipes, icy roads | F64: Test | G64: Y | H64: 0 | I64: 0 | J64: F | K64: - | L64: - | M64: - | N64: F | O64: Icy roads, cold-crack glass | P64: Realised weather
A65: dry_summer_index | B65: weather (policy year) | C65: num | D65: Dry summer 0-1 | E65: Clay shrinkage (subsidence), fire | F65: Exclude | G65: N | H65: 0 | I65: 0 | J65: - | K65: - | L65: - | M65: - | N65: - | O65: No motor mechanism | P65: Realised weather
A66: wildfire_index | B66: weather (policy year) | C66: num | D66: Wildfire 0-1 | E66: Fire hazard | F66: Exclude | G66: N | H66: 0 | I66: 0 | J66: - | K66: - | L66: - | M66: - | N66: - | O66: No motor fire peril | P66: Realised weather
A67: rainfall_mm | B67: weather (policy year) | C67: num | D67: Annual rainfall | E67: Flood, storm ingress, wet roads | F67: Test | G67: Y | H67: 0 | I67: 0 | J67: F | K67: - | L67: - | M67: - | N67: - | O67: Wet-road collisions | P67: Realised weather
A68: mean_temperature_c | B68: weather (policy year) | C68: num | D68: Mean temperature | E68: Freeze / drought conditions | F68: Exclude | G68: N | H68: 0 | I68: 0 | J68: - | K68: - | L68: - | M68: - | N68: - | O68: No clear motor mechanism | P68: Realised weather
A69: customer_age | B69: derived (2_clean) | C69: num | D69: Customer age at row start | E69: Duplicates driver_age / policyholder_age | F69: Exclude | G69: N | H69: 0 | I69: 0 | J69: - | K69: - | L69: - | M69: - | N69: - | O69: driver_age already covers the driving risk
A70: start_month | B70: derived (2_clean) | C70: num | D70: Row start month | E70: Seasonality of partial-year rows | F70: Test | G70: Y | H70: 0 | I70: 0 | J70: F | K70: F | L70: - | M70: F | N70: F | O70: Seasonality of partial-year rows
A71: years_with_insurer | B71: derived (2_clean) | C71: num | D71: policy_year - customer_since_year | E71: Duplicates renewal_count | F71: Exclude | G71: N | H71: 0 | I71: 0 | J71: - | K71: - | L71: - | M71: - | N71: - | O71: Duplicates renewal_count
A72: hist_policy_claims_prev | B72: derived (this script) | C72: num | D72: Positive claims on this policy with loss in prior year AND reported by end of prior year; NA if no prior-year row or year 2021 | E72: Own experience rating (renewal knowledge) | F72: Include | G72: Y | H72: 1 | I72: 0 | J72: F | K72: F | L72: F | M72: F | N72: F | O72: Own prior-year claims known at renewal (experience rating) | P72: Built only from info known at renewal - no leakage
A73: hist_customer_claims_other_lines_prev | B73: derived (this script) | C73: num | D73: Same customer's positive claims on the OTHER two lines, prior year, reported by its end; NA for 2021 | E73: Cross-line behaviour | F73: Test | G73: Y | H73: 1 | I73: 0 | J73: F | K73: F | L73: F | M73: F | N73: F | O73: Cross-line claims behaviour | P73: Built only from info known at renewal

Sheet Features_Buildings
A1: column | B1: source | C1: type | D1: description | E1: actuarial_role | F1: decision | G1: use | H1: mono_freq | I1: mono_sev | J1: storm | K1: flood | L1: escape_of_water | M1: subsidence | N1: fire | O1: accidental_damage | P1: reason | Q1: guardrail
A2: policyholder_age | B2: policies_buildings/contents | C2: num | D2: Policyholder age | E2: Household behaviour | F2: Test | G2: Y | H2: 0 | I2: 0 | J2: - | K2: - | L2: F | M2: - | N2: F | O2: F | P2: Household behaviour | Q2: Age is a permitted factor in most markets; check local rules
A3: sum_insured | B3: policies_buildings/contents | C3: num | D3: Sum insured (1000x unit errors fixed in 2_clean) | E3: Severity scale / rebuild cost | F3: Include | G3: Y | H3: 0 | I3: 1 | J3: S | K3: S | L3: B | M3: S | N3: S | O3: S | P3: Severity scale; size also drives EoW frequency
A4: construction_type | B4: policies_buildings | C4: cat | D4: brick/stone/timber/non_standard (T,W -> timber) | E4: Fire, storm, subsidence vulnerability | F4: Include | G4: Y | H4: 0 | I4: 0 | J4: B | K4: - | L4: F | M4: B | N4: B | O4: - | P4: Timber/non-standard: fire, storm, subsidence vulnerability | Q4: T/W -> timber is an inference
A5: occupancy | B5: policies_buildings | C5: cat | D5: Owner occupied / let | E5: Moral hazard, maintenance | F5: Include | G5: Y | H5: 0 | I5: 0 | J5: - | K5: - | L5: F | M5: - | N5: F | O5: F | P5: Let properties: maintenance and moral hazard
A6: days_unoccupied | B6: policies_buildings | C6: num | D6: Longest period unoccupied | E6: Undetected leaks, fire | F6: Include | G6: Y | H6: 1 | I6: 0 | J6: - | K6: - | L6: B | M6: - | N6: F | O6: - | P6: Undetected leaks; arson/fire
A7: smoke_alarms | B7: policies_buildings | C7: bool | D7: Smoke alarms present | E7: Fire mitigation | F7: Include | G7: Y | H7: 0 | I7: 0 | J7: - | K7: - | L7: - | M7: - | N7: B | O7: - | P7: Fire detection reduces frequency and size
A8: accidental_damage_cover | B8: policies_buildings/contents | C8: bool | D8: Optional AD cover | E8: Defines whether AD is covered (structural) | F8: Include | G8: Y | H8: 0 | I8: 0 | J8: - | K8: - | L8: - | M8: - | N8: - | O8: B | P8: Structural for AD peril | Q8: Structural zero when not bought - see Structural_Zeros
A9: mortgage | B9: policies_buildings | C9: bool | D9: Mortgaged | E9: Financial proxy only | F9: Exclude | G9: N | H9: 0 | I9: 0 | J9: - | K9: - | L9: - | M9: - | N9: - | O9: - | P9: Financial proxy only | Q9: No direct causal path
A10: voluntary_excess | B10: all policy files | C10: num | D10: Customer-chosen excess 0/250/500/1000 | E10: Removes small claims; self-selection | F10: Include | G10: Y | H10: -1 | I10: 0 | J10: B | K10: B | L10: B | M10: B | N10: B | O10: B | P10: Removes small claims; behaviour | Q10: Claims already net of excess - do not subtract again
A11: compulsory_excess | B11: all policy files | C11: num | D11: Insurer-set excess | E11: Removes small claims | F11: Include | G11: Y | H11: 0 | I11: 0 | J11: S | K11: S | L11: S | M11: S | N11: S | O11: S | P11: Applied per claim
A12: channel | B12: all policy files | C12: cat | D12: direct / comparison / broker | E12: Selection effect | F12: Test | G12: Y | H12: 0 | I12: 0 | J12: F | K12: - | L12: F | M12: - | N12: - | O12: F | P12: Selection
A13: payment_method | B13: all policy files | C13: cat | D13: annual / monthly | E13: Financial-stress proxy | F13: Test | G13: Y | H13: 0 | I13: 0 | J13: - | K13: - | L13: F | M13: - | N13: - | O13: F | P13: Financial-stress proxy (maintenance) | Q13: Proxy factor - document in guardrails
A14: missed_payments_12m | B14: all policy files | C14: num | D14: Missed payments last 12m | E14: Financial-stress proxy | F14: Test | G14: Y | H14: 1 | I14: 0 | J14: - | K14: - | L14: F | M14: - | N14: F | O14: F | P14: Financial-stress proxy | Q14: Proxy factor - document in guardrails
A15: new_business | B15: all policy files | C15: bool | D15: First year with insurer | E15: Selection / unknown risk | F15: Test | G15: Y | H15: 0 | I15: 0 | J15: - | K15: - | L15: F | M15: - | N15: - | O15: F | P15: Selection
A16: renewal_count | B16: all policy files | C16: num | D16: Previous renewals | E16: Tenure / survivorship | F16: Test | G16: Y | H16: 0 | I16: 0 | J16: - | K16: - | L16: F | M16: - | N16: - | O16: F | P16: Tenure | Q16: Survivorship bias: lapsed customers absent from test
A17: days_quote_to_inception | B17: all policy files | C17: num | D17: Days quote to start | E17: Anti-selection (last-minute buyers) | F17: Test | G17: Y | H17: 0 | I17: 0 | J17: F | K17: - | L17: F | M17: - | N17: - | O17: F | P17: Anti-selection (e.g. buying ahead of forecast storms)
A18: discount_applied | B18: all policy files | C18: num | D18: Discount on price | E18: Commercial decision, not risk | F18: Exclude | G18: N | H18: 0 | I18: 0 | J18: - | K18: - | L18: - | M18: - | N18: - | O18: - | P18: Commercial | Q18: Pricing decision - circular
A19: written_premium | B19: all policy files | C19: num | D19: Premium under current pricing | E19: Current price = old risk model + loadings | F19: Exclude | G19: N | H19: 0 | I19: 0 | J19: - | K19: - | L19: - | M19: - | N19: - | O19: - | P19: Circular; was top gain for flood in WENDY 3 - flood hazard now from flood_zone/elevation directly | Q19: Circular for a technical price review; also embeds expense/profit loadings
A20: occupation | B20: customers | C20: cat | D20: Occupation | E20: Lifestyle / use | F20: Exclude | G20: N | H20: 0 | I20: 0 | J20: - | K20: - | L20: - | M20: - | N20: - | O20: - | P20: Spurious in sparse perils | Q20: Potential proxy for protected traits - guardrail
A21: marital_status | B21: customers | C21: cat | D21: Marital status | E21: Driving behaviour proxy | F21: Exclude | G21: N | H21: 0 | I21: 0 | J21: - | K21: - | L21: - | M21: - | N21: - | O21: - | P21: No home mechanism | Q21: Sensitive in some markets - guardrail
A22: household_size | B22: customers | C22: num | D22: People in household | E22: Occupancy, AD, EoW usage | F22: Test | G22: Y | H22: 0 | I22: 0 | J22: - | K22: - | L22: F | M22: - | N22: F | O22: F | P22: Water usage, cooking fires, AD
A23: credit_band | B23: customers | C23: cat | D23: Credit band A-E | E23: Financial-stress / claims propensity | F23: Test | G23: Y | H23: 0 | I23: 0 | J23: - | K23: - | L23: F | M23: - | N23: F | O23: F | P23: Maintenance proxy; guardrail | Q23: Credit-based insurance scoring restricted in some markets - guardrail
A24: prior_claims_5y | B24: customers | C24: num | D24: Declared claims 5y before joining | E24: Claims history | F24: Include | G24: Y | H24: 1 | I24: 0 | J24: F | K24: F | L24: F | M24: F | N24: F | O24: F | P24: Declared history
A25: licence_points | B25: customers | C25: num | D25: Driving penalty points | E25: Driver conduct | F25: Exclude | G25: N | H25: 0 | I25: 0 | J25: - | K25: - | L25: - | M25: - | N25: - | O25: - | P25: Motor conduct, not home
A26: years_at_address | B26: customers | C26: num | D26: Years at address | E26: Stability | F26: Test | G26: Y | H26: 0 | I26: 0 | J26: - | K26: - | L26: F | M26: - | N26: - | O26: F | P26: Stability
A27: customer_since_year | B27: customers | C27: num | D27: First policy year | E27: Calendar cohort | F27: Exclude | G27: N | H27: 0 | I27: 0 | J27: - | K27: - | L27: - | M27: - | N27: - | O27: - | P27: Cohort year | Q27: Duplicates renewal_count; cohort year drifts out of range for 2025
A28: email_domain | B28: customers | C28: cat | D28: Anonymised email domain (~20% each) | E28: None - noise | F28: Exclude | G28: N | H28: 0 | I28: 0 | J28: - | K28: - | L28: - | M28: - | N28: - | O28: - | P28: Noise | Q28: Uniform; no causal path
A29: marketing_consent | B29: customers | C29: bool | D29: Marketing consent | E29: None | F29: Exclude | G29: N | H29: 0 | I29: 0 | J29: - | K29: - | L29: - | M29: - | N29: - | O29: - | P29: No causal path | Q29: No causal path
A30: document_preference | B30: customers | C30: cat | D30: email / post / app | E30: None (age proxy at best) | F30: Exclude | G30: N | H30: 0 | I30: 0 | J30: - | K30: - | L30: - | M30: - | N30: - | O30: - | P30: No causal path | Q30: Proxy only
A31: previous_insurer | B31: customers | C31: cat | D31: Previous insurer | E31: Weak selection signal | F31: Exclude | G31: N | H31: 0 | I31: 0 | J31: - | K31: - | L31: - | M31: - | N31: - | O31: - | P31: Spurious for fire/subsidence in WENDY 3 | Q31: Showed spurious top-10 importance for fire / subsidence in WENDY 3
A32: campaign_code | B32: customers | C32: cat | D32: Acquisition campaign | E32: Marketing | F32: Exclude | G32: N | H32: 0 | I32: 0 | J32: - | K32: - | L32: - | M32: - | N32: - | O32: - | P32: Spurious for subsidence in WENDY 3 | Q32: No causal path; null = no campaign
A33: branch_id | B33: customers | C33: cat | D33: Servicing branch | E33: Geography proxy (region already used) | F33: Exclude | G33: N | H33: 0 | I33: 0 | J33: - | K33: - | L33: - | M33: - | N33: - | O33: - | P33: Duplicates geography | Q33: Duplicates geography
A34: marketing_segment | B34: customers | C34: cat | D34: Marketing segment | E34: Opaque derived score | F34: Exclude | G34: N | H34: 0 | I34: 0 | J34: - | K34: - | L34: - | M34: - | N34: - | O34: - | P34: Opaque | Q34: Unknown construction - could encode price or protected traits
A35: region | B35: addresses | C35: cat | D35: Region R01-R12 | E35: Geography | F35: Include | G35: Y | H35: 0 | I35: 0 | J35: B | K35: B | L35: B | M35: B | N35: B | O35: B | P35: Geography, rebuild cost
A36: urban_density | B36: addresses | C36: cat | D36: rural ... dense_urban | E36: Traffic, crime density | F36: Test | G36: Y | H36: 0 | I36: 0 | J36: F | K36: - | L36: F | M36: - | N36: F | O36: F | P36: Arson, density
A37: flood_zone | B37: addresses | C37: num | D37: Flood zone 1-5 | E37: Flood hazard | F37: Include | G37: Y | H37: 1 | I37: 0 | J37: - | K37: B | L37: - | M37: - | N37: - | O37: - | P37: Flood hazard
A38: distance_to_river_km | B38: addresses | C38: num | D38: Distance to river | E38: Flood hazard | F38: Include | G38: Y | H38: -1 | I38: 0 | J38: - | K38: B | L38: - | M38: - | N38: - | O38: - | P38: Flood hazard
A39: elevation_m | B39: addresses | C39: num | D39: Height above river level | E39: Flood hazard | F39: Include | G39: Y | H39: -1 | I39: 0 | J39: - | K39: B | L39: - | M39: - | N39: - | O39: - | P39: Flood hazard
A40: soil_type | B40: addresses | C40: cat | D40: clay/sand/loam/chalk/rock | E40: Subsidence hazard (clay shrink-swell) | F40: Include | G40: Y | H40: 0 | I40: 0 | J40: - | K40: - | L40: - | M40: B | N40: - | O40: - | P40: Clay shrink-swell
A41: year_built | B41: addresses | C41: num | D41: Year built | E41: Plumbing age, construction standard | F41: Include | G41: Y | H41: 0 | I41: 0 | J41: B | K41: - | L41: B | M41: B | N41: F | O41: F | P41: Plumbing age, foundations, standards
A42: property_type | B42: addresses | C42: cat | D42: detached/semi/terraced/flat | E42: Exposure, flood floor level | F42: Include | G42: Y | H42: 0 | I42: 0 | J42: B | K42: B | L42: B | M42: B | N42: B | O42: F | P42: Exposure; flats rarely flood above ground floor
A43: roof_type | B43: addresses | C43: cat | D43: pitched / flat | E43: Storm and water ingress | F43: Include | G43: Y | H43: 0 | I43: 0 | J43: B | K43: - | L43: F | M43: - | N43: - | O43: - | P43: Flat roofs: storm and water ingress
A44: basement | B44: addresses | C44: bool | D44: Basement | E44: Flood / EoW / subsidence | F44: Include | G44: Y | H44: 0 | I44: 0 | J44: - | K44: B | L44: F | M44: F | N44: - | O44: - | P44: Flood / leak / subsidence
A45: trees_within_5m | B45: addresses | C45: bool | D45: Trees within 5m | E45: Subsidence (root shrinkage), storm debris | F45: Include | G45: Y | H45: 1 | I45: 0 | J45: F | K45: - | L45: - | M45: B | N45: - | O45: - | P45: Root shrinkage; storm debris
A46: listed_building | B46: addresses | C46: bool | D46: Listed building | E46: Rebuild cost (severity) | F46: Include | G46: Y | H46: 0 | I46: 0 | J46: S | K46: - | L46: S | M46: S | N46: S | O46: - | P46: Specialist rebuild cost
A47: bedrooms | B47: addresses | C47: num | D47: Bedrooms | E47: Size / severity | F47: Include | G47: Y | H47: 0 | I47: 0 | J47: S | K47: S | L47: S | M47: S | N47: S | O47: F | P47: Size / severity
A48: energy_rating | B48: addresses | C48: cat | D48: Energy rating A-G | E48: Building age / heating proxy | F48: Test | G48: Y | H48: 0 | I48: 0 | J48: - | K48: - | L48: F | M48: - | N48: F | O48: - | P48: Heating/age proxy; strong for fire in WENDY 3 | Q48: Proxy - keep only where it validates
A49: solar_panels | B49: addresses | C49: bool | D49: Solar panels | E49: Electrical fire, roof damage | F49: Test | G49: Y | H49: 0 | I49: 0 | J49: S | K49: - | L49: - | M49: - | N49: F | O49: - | P49: Electrical fire; roof damage cost
A50: hail_days | B50: weather (policy year) | C50: num | D50: Hail days in year | E50: Hail hazard | F50: Test | G50: Y | H50: 0 | I50: 0 | J50: F | K50: - | L50: - | M50: - | N50: - | O50: - | P50: Roof hail damage | Q50: Realised weather of the row's year (2025 supplied for test)
A51: wind_exposure_index | B51: weather (policy year) | C51: num | D51: Wind exposure 0-10 | E51: Storm hazard | F51: Include | G51: Y | H51: 1 | I51: 0 | J51: B | K51: - | L51: - | M51: - | N51: - | O51: - | P51: Storm hazard | Q51: Realised weather
A52: freezing_days | B52: weather (policy year) | C52: num | D52: Days below freezing | E52: Burst pipes, icy roads | F52: Include | G52: Y | H52: 1 | I52: 0 | J52: - | K52: - | L52: B | M52: - | N52: - | O52: - | P52: Burst pipes | Q52: Realised weather
A53: dry_summer_index | B53: weather (policy year) | C53: num | D53: Dry summer 0-1 | E53: Clay shrinkage (subsidence), fire | F53: Include | G53: Y | H53: 1 | I53: 0 | J53: - | K53: - | L53: - | M53: B | N53: F | O53: - | P53: Clay shrinkage; dry fires | Q53: Realised weather
A54: wildfire_index | B54: weather (policy year) | C54: num | D54: Wildfire 0-1 | E54: Fire hazard | F54: Include | G54: Y | H54: 1 | I54: 0 | J54: - | K54: - | L54: - | M54: - | N54: F | O54: - | P54: Fire hazard | Q54: Realised weather
A55: rainfall_mm | B55: weather (policy year) | C55: num | D55: Annual rainfall | E55: Flood, storm ingress, wet roads | F55: Include | G55: Y | H55: 0 | I55: 0 | J55: F | K55: B | L55: - | M55: F | N55: - | O55: - | P55: Flood; storm ingress; soil moisture | Q55: Realised weather
A56: mean_temperature_c | B56: weather (policy year) | C56: num | D56: Mean temperature | E56: Freeze / drought conditions | F56: Test | G56: Y | H56: 0 | I56: 0 | J56: - | K56: - | L56: F | M56: F | N56: - | O56: - | P56: Freeze / drought | Q56: Realised weather
A57: customer_age | B57: derived (2_clean) | C57: num | D57: Customer age at row start | E57: Duplicates driver_age / policyholder_age | F57: Exclude | G57: N | H57: 0 | I57: 0 | J57: - | K57: - | L57: - | M57: - | N57: - | O57: - | P57: Duplicates policyholder_age
A58: start_month | B58: derived (2_clean) | C58: num | D58: Row start month | E58: Seasonality of partial-year rows | F58: Test | G58: Y | H58: 0 | I58: 0 | J58: F | K58: - | L58: F | M58: F | N58: F | O58: - | P58: Seasonality of partial-year rows
A59: years_with_insurer | B59: derived (2_clean) | C59: num | D59: policy_year - customer_since_year | E59: Duplicates renewal_count | F59: Exclude | G59: N | H59: 0 | I59: 0 | J59: - | K59: - | L59: - | M59: - | N59: - | O59: - | P59: Duplicates renewal_count
A60: hist_policy_claims_prev | B60: derived (this script) | C60: num | D60: Positive claims on this policy with loss in prior year AND reported by end of prior year; NA if no prior-year row or year 2021 | E60: Own experience rating (renewal knowledge) | F60: Include | G60: Y | H60: 1 | I60: 0 | J60: F | K60: F | L60: F | M60: F | N60: F | O60: F | P60: Own prior-year claims | Q60: Built only from info known at renewal - no leakage
A61: hist_customer_claims_other_lines_prev | B61: derived (this script) | C61: num | D61: Same customer's positive claims on the OTHER two lines, prior year, reported by its end; NA for 2021 | E61: Cross-line behaviour | F61: Test | G61: Y | H61: 1 | I61: 0 | J61: F | K61: - | L61: F | M61: - | N61: - | O61: F | P61: Cross-line behaviour (non-weather perils) | Q61: Built only from info known at renewal

Sheet Features_Contents
A1: column | B1: source | C1: type | D1: description | E1: actuarial_role | F1: decision | G1: use | H1: mono_freq | I1: mono_sev | J1: theft | K1: escape_of_water | L1: accidental_damage | M1: flood | N1: reason | O1: guardrail
A2: policyholder_age | B2: policies_buildings/contents | C2: num | D2: Policyholder age | E2: Household behaviour | F2: Test | G2: Y | H2: 0 | I2: 0 | J2: F | K2: - | L2: F | M2: - | N2: Household behaviour | O2: Age is a permitted factor in most markets; check local rules
A3: sum_insured | B3: policies_buildings/contents | C3: num | D3: Sum insured (1000x unit errors fixed in 2_clean) | E3: Severity scale / rebuild cost | F3: Include | G3: Y | H3: 0 | I3: 1 | J3: B | K3: S | L3: B | M3: S | N3: Severity scale; more contents more theft/AD
A4: accidental_damage_cover | B4: policies_buildings/contents | C4: bool | D4: Optional AD cover | E4: Defines whether AD is covered (structural) | F4: Include | G4: Y | H4: 0 | I4: 0 | J4: - | K4: - | L4: B | M4: - | N4: Structural for AD peril | O4: Structural zero when not bought - see Structural_Zeros
A5: tenure | B5: policies_contents | C5: cat | D5: Owner / renter | E5: Theft, EoW exposure | F5: Include | G5: Y | H5: 0 | I5: 0 | J5: F | K5: F | L5: F | M5: F | N5: Renters: different exposure
A6: security_level | B6: policies_contents | C6: cat | D6: standard / locks / alarm_and_locks | E6: Theft mitigation | F6: Include | G6: Y | H6: 0 | I6: 0 | J6: B | K6: - | L6: - | M6: - | N6: Theft mitigation
A7: high_value_items | B7: policies_contents | C7: num | D7: Declared high-value items | E7: Theft attractiveness, severity | F7: Include | G7: Y | H7: 1 | I7: 0 | J7: B | K7: - | L7: S | M7: - | N7: Theft attractiveness and size
A8: works_from_home | B8: policies_contents | C8: bool | D8: Someone works from home | E8: Daytime occupancy (theft), AD | F8: Test | G8: Y | H8: 0 | I8: 0 | J8: F | K8: F | L8: F | M8: - | N8: Daytime occupancy
A9: lodgers | B9: policies_contents | C9: bool | D9: Lodgers/students in household | E9: Theft, AD | F9: Test | G9: Y | H9: 0 | I9: 0 | J9: F | K9: - | L9: F | M9: - | N9: Theft/AD by occupants
A10: bicycle_cover | B10: policies_contents | C10: bool | D10: Optional bicycle cover | E10: Adds bicycle theft exposure | F10: Include | G10: Y | H10: 0 | I10: 0 | J10: B | K10: - | L10: - | M10: - | N10: Adds bicycle theft exposure
A11: voluntary_excess | B11: all policy files | C11: num | D11: Customer-chosen excess 0/250/500/1000 | E11: Removes small claims; self-selection | F11: Include | G11: Y | H11: -1 | I11: 0 | J11: B | K11: B | L11: B | M11: B | N11: Removes small claims | O11: Claims already net of excess - do not subtract again
A12: compulsory_excess | B12: all policy files | C12: num | D12: Insurer-set excess | E12: Removes small claims | F12: Include | G12: Y | H12: 0 | I12: 0 | J12: S | K12: S | L12: S | M12: S | N12: Applied per claim
A13: channel | B13: all policy files | C13: cat | D13: direct / comparison / broker | E13: Selection effect | F13: Test | G13: Y | H13: 0 | I13: 0 | J13: F | K13: - | L13: F | M13: - | N13: Selection
A14: payment_method | B14: all policy files | C14: cat | D14: annual / monthly | E14: Financial-stress proxy | F14: Test | G14: Y | H14: 0 | I14: 0 | J14: F | K14: - | L14: F | M14: - | N14: Financial-stress proxy | O14: Proxy factor - document in guardrails
A15: missed_payments_12m | B15: all policy files | C15: num | D15: Missed payments last 12m | E15: Financial-stress proxy | F15: Test | G15: Y | H15: 1 | I15: 0 | J15: F | K15: - | L15: F | M15: - | N15: Financial-stress proxy | O15: Proxy factor - document in guardrails
A16: new_business | B16: all policy files | C16: bool | D16: First year with insurer | E16: Selection / unknown risk | F16: Test | G16: Y | H16: 0 | I16: 0 | J16: F | K16: F | L16: F | M16: - | N16: Selection
A17: renewal_count | B17: all policy files | C17: num | D17: Previous renewals | E17: Tenure / survivorship | F17: Test | G17: Y | H17: 0 | I17: 0 | J17: F | K17: F | L17: F | M17: - | N17: Tenure | O17: Survivorship bias: lapsed customers absent from test
A18: days_quote_to_inception | B18: all policy files | C18: num | D18: Days quote to start | E18: Anti-selection (last-minute buyers) | F18: Test | G18: Y | H18: 0 | I18: 0 | J18: F | K18: - | L18: F | M18: F | N18: Anti-selection
A19: discount_applied | B19: all policy files | C19: num | D19: Discount on price | E19: Commercial decision, not risk | F19: Exclude | G19: N | H19: 0 | I19: 0 | J19: - | K19: - | L19: - | M19: - | N19: Commercial | O19: Pricing decision - circular
A20: written_premium | B20: all policy files | C20: num | D20: Premium under current pricing | E20: Current price = old risk model + loadings | F20: Exclude | G20: N | H20: 0 | I20: 0 | J20: - | K20: - | L20: - | M20: - | N20: Circular; top gain for theft/EoW in WENDY 3 | O20: Circular for a technical price review; also embeds expense/profit loadings
A21: occupation | B21: customers | C21: cat | D21: Occupation | E21: Lifestyle / use | F21: Exclude | G21: N | H21: 0 | I21: 0 | J21: - | K21: - | L21: - | M21: - | N21: Proxy; not needed | O21: Potential proxy for protected traits - guardrail
A22: marital_status | B22: customers | C22: cat | D22: Marital status | E22: Driving behaviour proxy | F22: Exclude | G22: N | H22: 0 | I22: 0 | J22: - | K22: - | L22: - | M22: - | N22: No mechanism | O22: Sensitive in some markets - guardrail
A23: household_size | B23: customers | C23: num | D23: People in household | E23: Occupancy, AD, EoW usage | F23: Test | G23: Y | H23: 0 | I23: 0 | J23: F | K23: F | L23: F | M23: - | N23: Occupants
A24: credit_band | B24: customers | C24: cat | D24: Credit band A-E | E24: Financial-stress / claims propensity | F24: Test | G24: Y | H24: 0 | I24: 0 | J24: F | K24: F | L24: F | M24: - | N24: Claims propensity; guardrail | O24: Credit-based insurance scoring restricted in some markets - guardrail
A25: prior_claims_5y | B25: customers | C25: num | D25: Declared claims 5y before joining | E25: Claims history | F25: Include | G25: Y | H25: 1 | I25: 0 | J25: F | K25: F | L25: F | M25: F | N25: Declared history
A26: licence_points | B26: customers | C26: num | D26: Driving penalty points | E26: Driver conduct | F26: Exclude | G26: N | H26: 0 | I26: 0 | J26: - | K26: - | L26: - | M26: - | N26: Motor conduct
A27: years_at_address | B27: customers | C27: num | D27: Years at address | E27: Stability | F27: Test | G27: Y | H27: 0 | I27: 0 | J27: F | K27: F | L27: - | M27: - | N27: Stability
A28: customer_since_year | B28: customers | C28: num | D28: First policy year | E28: Calendar cohort | F28: Exclude | G28: N | H28: 0 | I28: 0 | J28: - | K28: - | L28: - | M28: - | N28: Cohort year | O28: Duplicates renewal_count; cohort year drifts out of range for 2025
A29: email_domain | B29: customers | C29: cat | D29: Anonymised email domain (~20% each) | E29: None - noise | F29: Exclude | G29: N | H29: 0 | I29: 0 | J29: - | K29: - | L29: - | M29: - | N29: Noise | O29: Uniform; no causal path
A30: marketing_consent | B30: customers | C30: bool | D30: Marketing consent | E30: None | F30: Exclude | G30: N | H30: 0 | I30: 0 | J30: - | K30: - | L30: - | M30: - | N30: No causal path | O30: No causal path
A31: document_preference | B31: customers | C31: cat | D31: email / post / app | E31: None (age proxy at best) | F31: Exclude | G31: N | H31: 0 | I31: 0 | J31: - | K31: - | L31: - | M31: - | N31: No causal path | O31: Proxy only
A32: previous_insurer | B32: customers | C32: cat | D32: Previous insurer | E32: Weak selection signal | F32: Exclude | G32: N | H32: 0 | I32: 0 | J32: - | K32: - | L32: - | M32: - | N32: No mechanism | O32: Showed spurious top-10 importance for fire / subsidence in WENDY 3
A33: campaign_code | B33: customers | C33: cat | D33: Acquisition campaign | E33: Marketing | F33: Exclude | G33: N | H33: 0 | I33: 0 | J33: - | K33: - | L33: - | M33: - | N33: Marketing | O33: No causal path; null = no campaign
A34: branch_id | B34: customers | C34: cat | D34: Servicing branch | E34: Geography proxy (region already used) | F34: Exclude | G34: N | H34: 0 | I34: 0 | J34: - | K34: - | L34: - | M34: - | N34: Duplicates geography | O34: Duplicates geography
A35: marketing_segment | B35: customers | C35: cat | D35: Marketing segment | E35: Opaque derived score | F35: Exclude | G35: N | H35: 0 | I35: 0 | J35: - | K35: - | L35: - | M35: - | N35: Opaque; ranked high for theft/EoW in WENDY 3 without a mechanism | O35: Unknown construction - could encode price or protected traits
A36: region | B36: addresses | C36: cat | D36: Region R01-R12 | E36: Geography | F36: Include | G36: Y | H36: 0 | I36: 0 | J36: B | K36: B | L36: B | M36: B | N36: Geography
A37: urban_density | B37: addresses | C37: cat | D37: rural ... dense_urban | E37: Traffic, crime density | F37: Include | G37: Y | H37: 0 | I37: 0 | J37: B | K37: - | L37: F | M37: - | N37: Crime density
A38: flood_zone | B38: addresses | C38: num | D38: Flood zone 1-5 | E38: Flood hazard | F38: Include | G38: Y | H38: 1 | I38: 0 | J38: - | K38: - | L38: - | M38: B | N38: Flood hazard
A39: distance_to_river_km | B39: addresses | C39: num | D39: Distance to river | E39: Flood hazard | F39: Include | G39: Y | H39: -1 | I39: 0 | J39: - | K39: - | L39: - | M39: B | N39: Flood hazard
A40: elevation_m | B40: addresses | C40: num | D40: Height above river level | E40: Flood hazard | F40: Include | G40: Y | H40: -1 | I40: 0 | J40: - | K40: - | L40: - | M40: B | N40: Flood hazard
A41: soil_type | B41: addresses | C41: cat | D41: clay/sand/loam/chalk/rock | E41: Subsidence hazard (clay shrink-swell) | F41: Exclude | G41: N | H41: 0 | I41: 0 | J41: - | K41: - | L41: - | M41: - | N41: No contents subsidence peril
A42: year_built | B42: addresses | C42: num | D42: Year built | E42: Plumbing age, construction standard | F42: Include | G42: Y | H42: 0 | I42: 0 | J42: - | K42: B | L42: - | M42: - | N42: Plumbing age
A43: property_type | B43: addresses | C43: cat | D43: detached/semi/terraced/flat | E43: Exposure, flood floor level | F43: Include | G43: Y | H43: 0 | I43: 0 | J43: F | K43: B | L43: F | M43: B | N43: Flats: theft access, flood floor level
A44: roof_type | B44: addresses | C44: cat | D44: pitched / flat | E44: Storm and water ingress | F44: Test | G44: Y | H44: 0 | I44: 0 | J44: - | K44: F | L44: - | M44: - | N44: Water ingress
A45: basement | B45: addresses | C45: bool | D45: Basement | E45: Flood / EoW / subsidence | F45: Include | G45: Y | H45: 0 | I45: 0 | J45: - | K45: F | L45: - | M45: B | N45: Flood / leaks
A46: trees_within_5m | B46: addresses | C46: bool | D46: Trees within 5m | E46: Subsidence (root shrinkage), storm debris | F46: Exclude | G46: N | H46: 0 | I46: 0 | J46: - | K46: - | L46: - | M46: - | N46: No mechanism
A47: listed_building | B47: addresses | C47: bool | D47: Listed building | E47: Rebuild cost (severity) | F47: Exclude | G47: N | H47: 0 | I47: 0 | J47: - | K47: - | L47: - | M47: - | N47: Building, not contents
A48: bedrooms | B48: addresses | C48: num | D48: Bedrooms | E48: Size / severity | F48: Test | G48: Y | H48: 0 | I48: 0 | J48: S | K48: S | L48: S | M48: S | N48: Size of household contents
A49: energy_rating | B49: addresses | C49: cat | D49: Energy rating A-G | E49: Building age / heating proxy | F49: Exclude | G49: N | H49: 0 | I49: 0 | J49: - | K49: - | L49: - | M49: - | N49: No mechanism | O49: Proxy - keep only where it validates
A50: solar_panels | B50: addresses | C50: bool | D50: Solar panels | E50: Electrical fire, roof damage | F50: Exclude | G50: N | H50: 0 | I50: 0 | J50: - | K50: - | L50: - | M50: - | N50: No mechanism
A51: hail_days | B51: weather (policy year) | C51: num | D51: Hail days in year | E51: Hail hazard | F51: Exclude | G51: N | H51: 0 | I51: 0 | J51: - | K51: - | L51: - | M51: - | N51: No contents hail peril | O51: Realised weather of the row's year (2025 supplied for test)
A52: wind_exposure_index | B52: weather (policy year) | C52: num | D52: Wind exposure 0-10 | E52: Storm hazard | F52: Exclude | G52: N | H52: 0 | I52: 0 | J52: - | K52: - | L52: - | M52: - | N52: No contents storm peril | O52: Realised weather
A53: freezing_days | B53: weather (policy year) | C53: num | D53: Days below freezing | E53: Burst pipes, icy roads | F53: Include | G53: Y | H53: 1 | I53: 0 | J53: - | K53: B | L53: - | M53: - | N53: Burst pipes | O53: Realised weather
A54: dry_summer_index | B54: weather (policy year) | C54: num | D54: Dry summer 0-1 | E54: Clay shrinkage (subsidence), fire | F54: Exclude | G54: N | H54: 0 | I54: 0 | J54: - | K54: - | L54: - | M54: - | N54: No mechanism | O54: Realised weather
A55: wildfire_index | B55: weather (policy year) | C55: num | D55: Wildfire 0-1 | E55: Fire hazard | F55: Exclude | G55: N | H55: 0 | I55: 0 | J55: - | K55: - | L55: - | M55: - | N55: No contents fire peril | O55: Realised weather
A56: rainfall_mm | B56: weather (policy year) | C56: num | D56: Annual rainfall | E56: Flood, storm ingress, wet roads | F56: Include | G56: Y | H56: 0 | I56: 0 | J56: - | K56: - | L56: - | M56: B | N56: Flood | O56: Realised weather
A57: mean_temperature_c | B57: weather (policy year) | C57: num | D57: Mean temperature | E57: Freeze / drought conditions | F57: Test | G57: Y | H57: 0 | I57: 0 | J57: - | K57: F | L57: - | M57: - | N57: Freeze conditions | O57: Realised weather
A58: customer_age | B58: derived (2_clean) | C58: num | D58: Customer age at row start | E58: Duplicates driver_age / policyholder_age | F58: Exclude | G58: N | H58: 0 | I58: 0 | J58: - | K58: - | L58: - | M58: - | N58: Duplicates policyholder_age
A59: start_month | B59: derived (2_clean) | C59: num | D59: Row start month | E59: Seasonality of partial-year rows | F59: Test | G59: Y | H59: 0 | I59: 0 | J59: F | K59: F | L59: - | M59: F | N59: Seasonality
A60: years_with_insurer | B60: derived (2_clean) | C60: num | D60: policy_year - customer_since_year | E60: Duplicates renewal_count | F60: Exclude | G60: N | H60: 0 | I60: 0 | J60: - | K60: - | L60: - | M60: - | N60: Duplicates renewal_count
A61: hist_policy_claims_prev | B61: derived (this script) | C61: num | D61: Positive claims on this policy with loss in prior year AND reported by end of prior year; NA if no prior-year row or year 2021 | E61: Own experience rating (renewal knowledge) | F61: Include | G61: Y | H61: 1 | I61: 0 | J61: F | K61: F | L61: F | M61: F | N61: Own prior-year claims | O61: Built only from info known at renewal - no leakage
A62: hist_customer_claims_other_lines_prev | B62: derived (this script) | C62: num | D62: Same customer's positive claims on the OTHER two lines, prior year, reported by its end; NA for 2021 | E62: Cross-line behaviour | F62: Test | G62: Y | H62: 1 | I62: 0 | J62: F | K62: F | L62: F | M62: - | N62: Cross-line behaviour | O62: Built only from info known at renewal

Sheet Model_Spec
A1: line | B1: peril | C1: freq_model | D1: sev_model | E1: challenger_tweedie | F1: cap_quantile | G1: sev_trend | H1: freq_trend | I1: sev_exclude_recent_years | J1: freq_max_depth | K1: freq_eta | L1: freq_min_child_weight | M1: sev_max_depth | N1: sev_eta | O1: sev_min_child_weight | P1: tweedie_p | Q1: rationale
A2: motor | B2: own_damage | C2: poisson_gbm | D2: gamma_gbm | E2: Y | F2: 0.999 | G2: estimate | H2: estimate | I2: 0 | J2: 4 | K2: 0.05 | L2: 50 | M2: 3 | N2: 0.05 | O2: 100 | P2: 1.5 | Q2: ~49k claims: data-rich, GBM for both parts.
A3: motor | B3: third_party_prop | C3: poisson_gbm | D3: gamma_gbm | E3: Y | F3: 0.999 | G3: estimate | H3: estimate | I3: 0 | J3: 4 | K3: 0.05 | L3: 50 | M3: 3 | N3: 0.05 | O3: 100 | P3: 1.5 | Q3: ~34k claims: data-rich.
A4: motor | B4: bodily_injury | C4: poisson_gbm | D4: gamma_glm | E4: Y | F4: 0.995 | G4: none | H4: none | I4: 1 | J4: 3 | K4: 0.05 | L4: 100 | M4: 0 | N4: 0 | O4: 0 | P4: 1.6 | Q4: ~7.6k claims, long tail (median report lag ~127 days), 2024 immature: Poisson GBM frequency + Gamma GLM severity on few factors; latest year left out of severity fit.
A5: motor | B5: theft | C5: poisson_gbm | D5: gamma_glm | E5: Y | F5: 0.999 | G5: estimate | H5: none | I5: 0 | J5: 3 | K5: 0.05 | L5: 50 | M5: 3 | N5: 0.05 | O5: 100 | P5: 1.5 | Q5: ~6.5k claims; recoveries matter.
A6: motor | B6: glass_hail | C6: poisson_gbm | D6: gamma_gbm | E6: Y | F6: 0.999 | G6: estimate | H6: none | I6: 0 | J6: 3 | K6: 0.05 | L6: 50 | M6: 3 | N6: 0.05 | O6: 100 | P6: 1.5 | Q6: Weather-driven: no frequency trend.
A7: buildings | B7: storm | C7: poisson_gbm | D7: gamma_gbm | E7: Y | F7: 0.999 | G7: estimate | H7: none | I7: 0 | J7: 3 | K7: 0.05 | L7: 50 | M7: 3 | N7: 0.05 | O7: 100 | P7: 1.5 | Q7: ~7.8k claims; weather-driven.
A8: buildings | B8: flood | C8: poisson_gbm | D8: gamma_glm | E8: Y | F8: 0.995 | G8: estimate | H8: none | I8: 0 | J8: 3 | K8: 0.05 | L8: 30 | M8: 0 | N8: 0 | O8: 0 | P8: 1.6 | Q8: ~2.2k claims, strong hazard structure: GBM frequency, GLM severity.
A9: buildings | B9: escape_of_water | C9: poisson_gbm | D9: gamma_glm | E9: Y | F9: 0.999 | G9: estimate | H9: none | I9: 0 | J9: 4 | K9: 0.05 | L9: 50 | M9: 3 | N9: 0.05 | O9: 100 | P9: 1.5 | Q9: ~10k claims: data-rich.
A10: buildings | B10: subsidence | C10: poisson_gbm | D10: gamma_glm | E10: Y | F10: 0.995 | G10: estimate | H10: none | I10: 1 | J10: 3 | K10: 0.05 | L10: 30 | M10: 0 | N10: 0 | O10: 0 | P10: 1.6 | Q10: ~1.3k claims, long tail (median lag ~94 days): GLM severity, latest year excluded from severity.
A11: buildings | B11: fire | C11: poisson_gbm | D11: gamma_glm | E11: Y | F11: 0.99 | G11: estimate | H11: none | I11: 0 | J11: 3 | K11: 0.05 | L11: 15 | M11: 0 | N11: 0 | O11: 0 | P11: 1.7 | Q11: ~1.1k claims, very heavy severity: GLM severity, lower cap.
A12: buildings | B12: accidental_damage | C12: poisson_gbm | D12: gamma_gbm | E12: Y | F12: 0.999 | G12: estimate | H12: none | I12: 0 | J12: 3 | K12: 0.05 | L12: 30 | M12: 3 | N12: 0.05 | O12: 100 | P12: 1.5 | Q12: ~3.8k claims; structural zero without AD cover.
A13: contents | B13: theft | C13: poisson_gbm | D13: gamma_glm | E13: Y | F13: 0.999 | G13: estimate | H13: none | I13: 0 | J13: 4 | K13: 0.05 | L13: 50 | M13: 3 | N13: 0.05 | O13: 100 | P13: 1.5 | Q13: ~7.9k claims.
... A16: contents | B16: flood | C16: poisson_gbm | D16: gamma_glm | E16: Y | F16: 0.995 | G16: estimate | H16: none | I16: 0 | J16: 3 | K16: 0.05 | L16: 30 | M16: 0 | N16: 0 | O16: 0 | P16: 1.6 | Q16: ~1.6k claims: GLM severity.
A18: Notes
A19: freq_min_child_weight ~ minimum expected claim count per leaf (Poisson hessian ~ expected count; xgboost's max_delta_step inflates it roughly 2x - approximate).
A20: sev_min_child_weight ~ minimum claims per leaf for the Gamma GBM. sev_* depth/eta are ignored when sev_model = gamma_glm.
A21: sev_trend / freq_trend: estimate = fit inside each training window and clamp to the Settings bounds; none = no trend.
A22: cap_quantile is taken over that peril's positive claim costs in the training window (after the outlier limit and trend).

Sheet Structural_Zeros
A1: line | B1: peril | C1: column | D1: values | E1: rationale
A2: motor | B2: own_damage | C2: cover_type | D2: third_party_only,third_party_fire_theft | E2: Own damage is only covered by comprehensive.
A3: motor | B3: glass_hail | C3: cover_type | D3: third_party_only,third_party_fire_theft | E3: Glass is normally a comprehensive benefit (assumption - the data check decides).
A4: motor | B4: theft | C4: cover_type | D4: third_party_only | E4: Theft is covered by TPFT and comprehensive only.
A5: buildings | B5: accidental_damage | C5: accidental_damage_cover | D5: FALSE | E5: AD only covered if bought.
A6: contents | B6: accidental_damage | C6: accidental_damage_cover | D6: FALSE | E6: AD only covered if bought.
A8: A rule is applied only if the training data has ZERO positive claims of that peril in those rows; otherwise the script warns and ignores it. Values are matched case-insensitively against the column as text.

Sheet Settings
A1: key | B1: value | C1: note
A2: valid_years | B2: 2023,2024 | C2: Out-of-time folds: each is fitted on all earlier years.
A3: target_year | B3: 2025 | C3: Year the submission predicts (trend target).
A4: lag_loss_years | B4: 2021,2022 | C4: Loss years whose report lags define the reporting pattern.
A5: outlier_claim_limit | B5: 2000000 | C5: Single-claim limit applied before caps (CU).
A6: sev_trend_min | B6: -0.02 | C6: Lower clamp on annual severity trend.
A7: sev_trend_max | B7: 0.10 | C7: Upper clamp on annual severity trend.
A8: freq_trend_min | B8: -0.05 | C8: Lower clamp on annual frequency trend.
A9: freq_trend_max | B9: 0.03 | C9: Upper clamp on annual frequency trend.
A10: model_selection | B10: auto | C10: auto = better of freq_sev / tweedie per peril by mean validation D2; freq_sev or tweedie forces one.
A11: open_claim_recovery_adjust | B11: Y | C11: Deduct expected recoveries from OPEN claims of perils with recoveries (closed recovery ratio).
A12: history_features | B12: Y | C12: Build hist_* prior-year claims features (Y/N).
A13: max_rounds | B13: 3000 | C13: Max boosting rounds (early stopping decides).
A14: early_stopping_rounds | B14: 50
A15: holdout_share | B15: 0.10 | C15: Share of training POLICIES held out for early stopping.
A16: subsample | B16: 0.8 | C16: Row subsample per tree.
A17: colsample_bytree | B17: 0.8 | C17: Feature subsample per tree.
A18: reg_lambda | B18: 5 | C18: L2 regularisation.
A19: glm_min_level_claims | B19: 30 | C19: GLM severity: category levels with fewer claims are pooled into 'other'.
A20: glm_log_features | B20: sum_insured,annual_mileage,distance_to_river_km | C20: Numeric features entered as log(1+x) in GLM severity.
A21: score_tweedie_p | B21: 1.5 | C21: Power of the Tweedie D2 metric (Kaggle).
A22: nthread | B22: 0 | C22: 0 = all cores.
A23: ibnr_method | B23: chain_ladder | C23: WENDY 7: reported-count chain ladder per peril (loss quarter x development quarter, 2021-24 losses).
A24: ibnr_override | B24: buildings/subsidence=report_share_days | C24: Per-peril IBNR method: subsidence uses the lag ECDF averaged over the row's days (sparse triangle).
A25: bags | B25: 5 | C25: WENDY 7: each xgboost component = mean of 5 boosters (own policy holdout, seed SEED + b); bag 1 = WENDY 4 fit.
A26: method_mix | B26: sheet | C26: WENDY 7: freq_sev / tweedie per peril read from sheet Method_Mix (environment METHOD_MIX overrides).

Sheet Column_Register
A1: column | B1: source | C1: description | D1: actuarial_role | E1: motor | F1: buildings | G1: contents | H1: guardrail
A2: row_id | B2: all policy files | C2: Row key | D2: Identifier | E2: n/a | F2: n/a | G2: n/a | H2: Identifier - excluded
A3: policy_id | B3: all policy files | C3: Policy key (constant across years) | D3: Identifier; used to build history and holdouts | E3: n/a | F3: n/a | G3: n/a | H3: Identifier - excluded
A4: customer_id | B4: all policy files | C4: Customer key (leading zeros fixed) | D4: Identifier; used for cross-line history | E4: n/a | F4: n/a | G4: n/a | H4: Identifier - excluded
A5: address_id | B5: all policy files | C5: Address key | D5: Join key to addresses/weather | E5: n/a | F5: n/a | G5: n/a | H5: Identifier - excluded
A6: period_start / period_end | B6: all policy files | C6: Cover dates | D6: Exposure, IBNR share, start_month | E6: n/a | F6: n/a | G6: n/a | H6: Raw dates excluded
A7: exposure | B7: all policy files | C7: Years on cover (recomputed) | D7: Frequency volume | E7: n/a | F7: n/a | G7: n/a | H7: Volume, not a feature
A8: renewal_decision | B8: train only | C8: Row outcome | D8: LEAKAGE | E8: n/a | F8: n/a | G8: n/a | H8: Dropped in 2_clean
A9: customer_service_contacts | B9: all policy files | C9: Service contacts | D9: LEAKAGE | E9: n/a | F9: n/a | G9: n/a | H9: Excluded in 0_setup
A10: surname | B10: customers | C10: Anonymised surname | D10: None | E10: n/a | F10: n/a | G10: n/a | H10: Dropped (possible ethnicity proxy)
A11: date_of_birth | B11: customers | C11: DOB | D11: Becomes customer_age | E11: n/a | F11: n/a | G11: n/a | H11: Raw date dropped
A12: claim_id | B12: claims | C12: Claim key | D12: Identifier | E12: n/a | F12: n/a | G12: n/a | H12: -
... A20: repairer_id / third_party_id | B20: claims | C20: Motor claim parties | D20: Not known for test rows | E20: n/a | F20: n/a | G20: n/a | H20: Excluded
A21: driver_age | B21: policies_motor | C21: Main driver age at row start | D21: Driver risk | E21: =IFERROR(INDEX(Features_Motor!$F:$F,MATCH($A21,Features_Motor!$A:$A,0)),"n/a") -> Include | F21: =IFERROR(INDEX(Features_Buildings!$F:$F,MATCH($A21,Features_Buildings!$A:$A,0)),"n/a") -> n/a | G21: =IFERROR(INDEX(Features_Contents!$F:$F,MATCH($A21,Features_Contents!$A:$A,0)),"n/a") -> n/a
A22: years_licensed | B22: policies_motor | C22: Years main driver licensed (capped at age-16) | D22: Driver experience | E22: =IFERROR(INDEX(Features_Motor!$F:$F,MATCH($A22,Features_Motor!$A:$A,0)),"n/a") -> Include | F22: =IFERROR(INDEX(Features_Buildings!$F:$F,MATCH($A22,Features_Buildings!$A:$A,0)),"n/a") -> n/a | G22: =IFERROR(INDEX(Features_Contents!$F:$F,MATCH($A22,Features_Contents!$A:$A,0)),"n/a") -> n/a
A23: ncb_years | B23: policies_motor | C23: No-claims bonus years | D23: Claims history / experience | E23: =IFERROR(INDEX(Features_Motor!$F:$F,MATCH($A23,Features_Motor!$A:$A,0)),"n/a") -> Include | F23: =IFERROR(INDEX(Features_Buildings!$F:$F,MATCH($A23,Features_Buildings!$A:$A,0)),"n/a") -> n/a | G23: =IFERROR(INDEX(Features_Contents!$F:$F,MATCH($A23,Features_Contents!$A:$A,0)),"n/a") -> n/a
A24: vehicle_value_group | B24: policies_motor | C24: Vehicle value band 1-20 | D24: Exposure to damage / theft severity | E24: =IFERROR(INDEX(Features_Motor!$F:$F,MATCH($A24,Features_Motor!$A:$A,0)),"n/a") -> Include | F24: =IFERROR(INDEX(Features_Buildings!$F:$F,MATCH($A24,Features_Buildings!$A:$A,0)),"n/a") -> n/a | G24: =IFERROR(INDEX(Features_Contents!$F:$F,MATCH($A24,Features_Contents!$A:$A,0)),"n/a") -> n/a
A25: vehicle_age | B25: policies_motor | C25: Vehicle age | D25: Repair cost, theft attractiveness | E25: =IFERROR(INDEX(Features_Motor!$F:$F,MATCH($A25,Features_Motor!$A:$A,0)),"n/a") -> Include | F25: =IFERROR(INDEX(Features_Buildings!$F:$F,MATCH($A25,Features_Buildings!$A:$A,0)),"n/a") -> n/a | G25: =IFERROR(INDEX(Features_Contents!$F:$F,MATCH($A25,Features_Contents!$A:$A,0)),"n/a") -> n/a
A26: make_model | B26: policies_motor | C26: Anonymised make/model code (high cardinality) | D26: Vehicle repair cost / theft target | E26: =IFERROR(INDEX(Features_Motor!$F:$F,MATCH($A26,Features_Motor!$A:$A,0)),"n/a") -> Test | F26: =IFERROR(INDEX(Features_Buildings!$F:$F,MATCH($A26,Features_Buildings!$A:$A,0)),"n/a") -> n/a | G26: =IFERROR(INDEX(Features_Contents!$F:$F,MATCH($A26,Features_Contents!$A:$A,0)),"n/a") -> n/a | H26: High cardinality - encoded by training rate order; overfit risk on sparse perils
A27: engine_size_cc | B27: policies_motor | C27: Engine size | D27: Performance / driving style | E27: =IFERROR(INDEX(Features_Motor!$F:$F,MATCH($A27,Features_Motor!$A:$A,0)),"n/a") -> Include | F27: =IFERROR(INDEX(Features_Buildings!$F:$F,MATCH($A27,Features_Buildings!$A:$A,0)),"n/a") -> n/a | G27: =IFERROR(INDEX(Features_Contents!$F:$F,MATCH($A27,Features_Contents!$A:$A,0)),"n/a") -> n/a
A28: body_type | B28: policies_motor | C28: Body type | D28: Repair cost, use pattern | E28: =IFERROR(INDEX(Features_Motor!$F:$F,MATCH($A28,Features_Motor!$A:$A,0)),"n/a") -> Include | F28: =IFERROR(INDEX(Features_Buildings!$F:$F,MATCH($A28,Features_Buildings!$A:$A,0)),"n/a") -> n/a | G28: =IFERROR(INDEX(Features_Contents!$F:$F,MATCH($A28,Features_Contents!$A:$A,0)),"n/a") -> n/a
A29: transmission | B29: policies_motor | C29: Manual / automatic | D29: Weak driving-style proxy | E29: =IFERROR(INDEX(Features_Motor!$F:$F,MATCH($A29,Features_Motor!$A:$A,0)),"n/a") -> Test | F29: =IFERROR(INDEX(Features_Buildings!$F:$F,MATCH($A29,Features_Buildings!$A:$A,0)),"n/a") -> n/a | G29: =IFERROR(INDEX(Features_Contents!$F:$F,MATCH($A29,Features_Contents!$A:$A,0)),"n/a") -> n/a
A30: seats | B30: policies_motor | C30: Seats | D30: Occupants exposed to injury | E30: =IFERROR(INDEX(Features_Motor!$F:$F,MATCH($A30,Features_Motor!$A:$A,0)),"n/a") -> Test | F30: =IFERROR(INDEX(Features_Buildings!$F:$F,MATCH($A30,Features_Buildings!$A:$A,0)),"n/a") -> n/a | G30: =IFERROR(INDEX(Features_Contents!$F:$F,MATCH($A30,Features_Contents!$A:$A,0)),"n/a") -> n/a
A31: vehicle_colour | B31: policies_motor | C31: Colour (~12.5% each, uniform) | D31: None - noise | E31: =IFERROR(INDEX(Features_Motor!$F:$F,MATCH($A31,Features_Motor!$A:$A,0)),"n/a") -> Exclude | F31: =IFERROR(INDEX(Features_Buildings!$F:$F,MATCH($A31,Features_Buildings!$A:$A,0)),"n/a") -> n/a | G31: =IFERROR(INDEX(Features_Contents!$F:$F,MATCH($A31,Features_Contents!$A:$A,0)),"n/a") -> n/a | H31: No causal path; uniform distribution suggests synthetic noise
A32: fuel_type | B32: policies_motor | C32: Petrol/diesel/hybrid/electric | D32: EV repair cost, theft target | E32: =IFERROR(INDEX(Features_Motor!$F:$F,MATCH($A32,Features_Motor!$A:$A,0)),"n/a") -> Test | F32: =IFERROR(INDEX(Features_Buildings!$F:$F,MATCH($A32,Features_Buildings!$A:$A,0)),"n/a") -> n/a | G32: =IFERROR(INDEX(Features_Contents!$F:$F,MATCH($A32,Features_Contents!$A:$A,0)),"n/a") -> n/a
A33: driver_assist | B33: policies_motor | C33: Driver-assistance tech | D33: Collision avoidance | E33: =IFERROR(INDEX(Features_Motor!$F:$F,MATCH($A33,Features_Motor!$A:$A,0)),"n/a") -> Include | F33: =IFERROR(INDEX(Features_Buildings!$F:$F,MATCH($A33,Features_Buildings!$A:$A,0)),"n/a") -> n/a | G33: =IFERROR(INDEX(Features_Contents!$F:$F,MATCH($A33,Features_Contents!$A:$A,0)),"n/a") -> n/a
A34: cover_type | B34: policies_motor | C34: comprehensive / TPFT / TPO | D34: Defines which perils are covered (structural) | E34: =IFERROR(INDEX(Features_Motor!$F:$F,MATCH($A34,Features_Motor!$A:$A,0)),"n/a") -> Include | F34: =IFERROR(INDEX(Features_Buildings!$F:$F,MATCH($A34,Features_Buildings!$A:$A,0)),"n/a") -> n/a | G34: =IFERROR(INDEX(Features_Contents!$F:$F,MATCH($A34,Features_Contents!$A:$A,0)),"n/a") -> n/a | H34: Structural zeros enforced - see Structural_Zeros
A35: annual_mileage | B35: policies_motor | C35: Declared mileage | D35: Exposure to road risk | E35: =IFERROR(INDEX(Features_Motor!$F:$F,MATCH($A35,Features_Motor!$A:$A,0)),"n/a") -> Include | F35: =IFERROR(INDEX(Features_Buildings!$F:$F,MATCH($A35,Features_Buildings!$A:$A,0)),"n/a") -> n/a | G35: =IFERROR(INDEX(Features_Contents!$F:$F,MATCH($A35,Features_Contents!$A:$A,0)),"n/a") -> n/a
A36: overnight_parking | B36: policies_motor | C36: Garage / driveway / street | D36: Theft, hail, vandalism | E36: =IFERROR(INDEX(Features_Motor!$F:$F,MATCH($A36,Features_Motor!$A:$A,0)),"n/a") -> Include | F36: =IFERROR(INDEX(Features_Buildings!$F:$F,MATCH($A36,Features_Buildings!$A:$A,0)),"n/a") -> n/a | G36: =IFERROR(INDEX(Features_Contents!$F:$F,MATCH($A36,Features_Contents!$A:$A,0)),"n/a") -> n/a
A37: vehicle_use | B37: policies_motor | C37: Social / commuting / business | D37: Road exposure | E37: =IFERROR(INDEX(Features_Motor!$F:$F,MATCH($A37,Features_Motor!$A:$A,0)),"n/a") -> Include | F37: =IFERROR(INDEX(Features_Buildings!$F:$F,MATCH($A37,Features_Buildings!$A:$A,0)),"n/a") -> n/a | G37: =IFERROR(INDEX(Features_Contents!$F:$F,MATCH($A37,Features_Contents!$A:$A,0)),"n/a") -> n/a
A38: named_young_driver | B38: policies_motor | C38: Under-25 named driver | D38: Driver risk | E38: =IFERROR(INDEX(Features_Motor!$F:$F,MATCH($A38,Features_Motor!$A:$A,0)),"n/a") -> Include | F38: =IFERROR(INDEX(Features_Buildings!$F:$F,MATCH($A38,Features_Buildings!$A:$A,0)),"n/a") -> n/a | G38: =IFERROR(INDEX(Features_Contents!$F:$F,MATCH($A38,Features_Contents!$A:$A,0)),"n/a") -> n/a
A39: telematics_opt_in | B39: policies_motor | C39: Telematics opt-in | D39: Self-selection signal | E39: =IFERROR(INDEX(Features_Motor!$F:$F,MATCH($A39,Features_Motor!$A:$A,0)),"n/a") -> Test | F39: =IFERROR(INDEX(Features_Buildings!$F:$F,MATCH($A39,Features_Buildings!$A:$A,0)),"n/a") -> n/a | G39: =IFERROR(INDEX(Features_Contents!$F:$F,MATCH($A39,Features_Contents!$A:$A,0)),"n/a") -> n/a
A40: telematics_score | B40: policies_motor | C40: Score 1-100, NA if not opted in | D40: Observed driving behaviour | E40: =IFERROR(INDEX(Features_Motor!$F:$F,MATCH($A40,Features_Motor!$A:$A,0)),"n/a") -> Test | F40: =IFERROR(INDEX(Features_Buildings!$F:$F,MATCH($A40,Features_Buildings!$A:$A,0)),"n/a") -> n/a | G40: =IFERROR(INDEX(Features_Contents!$F:$F,MATCH($A40,Features_Contents!$A:$A,0)),"n/a") -> n/a | H40: NA by design; GBM handles NA natively
A41: policyholder_age | B41: policies_buildings/contents | C41: Policyholder age | D41: Household behaviour | E41: =IFERROR(INDEX(Features_Motor!$F:$F,MATCH($A41,Features_Motor!$A:$A,0)),"n/a") -> n/a | F41: =IFERROR(INDEX(Features_Buildings!$F:$F,MATCH($A41,Features_Buildings!$A:$A,0)),"n/a") -> Test | G41: =IFERROR(INDEX(Features_Contents!$F:$F,MATCH($A41,Features_Contents!$A:$A,0)),"n/a") -> Test | H41: Age is a permitted factor in most markets; check local rules
A42: sum_insured | B42: policies_buildings/contents | C42: Sum insured (1000x unit errors fixed in 2_clean) | D42: Severity scale / rebuild cost | E42: =IFERROR(INDEX(Features_Motor!$F:$F,MATCH($A42,Features_Motor!$A:$A,0)),"n/a") -> n/a | F42: =IFERROR(INDEX(Features_Buildings!$F:$F,MATCH($A42,Features_Buildings!$A:$A,0)),"n/a") -> Include | G42: =IFERROR(INDEX(Features_Contents!$F:$F,MATCH($A42,Features_Contents!$A:$A,0)),"n/a") -> Include
A43: construction_type | B43: policies_buildings | C43: brick/stone/timber/non_standard (T,W -> timber) | D43: Fire, storm, subsidence vulnerability | E43: =IFERROR(INDEX(Features_Motor!$F:$F,MATCH($A43,Features_Motor!$A:$A,0)),"n/a") -> n/a | F43: =IFERROR(INDEX(Features_Buildings!$F:$F,MATCH($A43,Features_Buildings!$A:$A,0)),"n/a") -> Include | G43: =IFERROR(INDEX(Features_Contents!$F:$F,MATCH($A43,Features_Contents!$A:$A,0)),"n/a") -> n/a | H43: T/W -> timber is an inference
A44: occupancy | B44: policies_buildings | C44: Owner occupied / let | D44: Moral hazard, maintenance | E44: =IFERROR(INDEX(Features_Motor!$F:$F,MATCH($A44,Features_Motor!$A:$A,0)),"n/a") -> n/a | F44: =IFERROR(INDEX(Features_Buildings!$F:$F,MATCH($A44,Features_Buildings!$A:$A,0)),"n/a") -> Include | G44: =IFERROR(INDEX(Features_Contents!$F:$F,MATCH($A44,Features_Contents!$A:$A,0)),"n/a") -> n/a
A45: days_unoccupied | B45: policies_buildings | C45: Longest period unoccupied | D45: Undetected leaks, fire | E45: =IFERROR(INDEX(Features_Motor!$F:$F,MATCH($A45,Features_Motor!$A:$A,0)),"n/a") -> n/a | F45: =IFERROR(INDEX(Features_Buildings!$F:$F,MATCH($A45,Features_Buildings!$A:$A,0)),"n/a") -> Include | G45: =IFERROR(INDEX(Features_Contents!$F:$F,MATCH($A45,Features_Contents!$A:$A,0)),"n/a") -> n/a
A46: smoke_alarms | B46: policies_buildings | C46: Smoke alarms present | D46: Fire mitigation | E46: =IFERROR(INDEX(Features_Motor!$F:$F,MATCH($A46,Features_Motor!$A:$A,0)),"n/a") -> n/a | F46: =IFERROR(INDEX(Features_Buildings!$F:$F,MATCH($A46,Features_Buildings!$A:$A,0)),"n/a") -> Include | G46: =IFERROR(INDEX(Features_Contents!$F:$F,MATCH($A46,Features_Contents!$A:$A,0)),"n/a") -> n/a
A47: accidental_damage_cover | B47: policies_buildings/contents | C47: Optional AD cover | D47: Defines whether AD is covered (structural) | E47: =IFERROR(INDEX(Features_Motor!$F:$F,MATCH($A47,Features_Motor!$A:$A,0)),"n/a") -> n/a | F47: =IFERROR(INDEX(Features_Buildings!$F:$F,MATCH($A47,Features_Buildings!$A:$A,0)),"n/a") -> Include | G47: =IFERROR(INDEX(Features_Contents!$F:$F,MATCH($A47,Features_Contents!$A:$A,0)),"n/a") -> Include | H47: Structural zero when not bought - see Structural_Zeros
A48: mortgage | B48: policies_buildings | C48: Mortgaged | D48: Financial proxy only | E48: =IFERROR(INDEX(Features_Motor!$F:$F,MATCH($A48,Features_Motor!$A:$A,0)),"n/a") -> n/a | F48: =IFERROR(INDEX(Features_Buildings!$F:$F,MATCH($A48,Features_Buildings!$A:$A,0)),"n/a") -> Exclude | G48: =IFERROR(INDEX(Features_Contents!$F:$F,MATCH($A48,Features_Contents!$A:$A,0)),"n/a") -> n/a | H48: No direct causal path
A49: tenure | B49: policies_contents | C49: Owner / renter | D49: Theft, EoW exposure | E49: =IFERROR(INDEX(Features_Motor!$F:$F,MATCH($A49,Features_Motor!$A:$A,0)),"n/a") -> n/a | F49: =IFERROR(INDEX(Features_Buildings!$F:$F,MATCH($A49,Features_Buildings!$A:$A,0)),"n/a") -> n/a | G49: =IFERROR(INDEX(Features_Contents!$F:$F,MATCH($A49,Features_Contents!$A:$A,0)),"n/a") -> Include
A50: security_level | B50: policies_contents | C50: standard / locks / alarm_and_locks | D50: Theft mitigation | E50: =IFERROR(INDEX(Features_Motor!$F:$F,MATCH($A50,Features_Motor!$A:$A,0)),"n/a") -> n/a | F50: =IFERROR(INDEX(Features_Buildings!$F:$F,MATCH($A50,Features_Buildings!$A:$A,0)),"n/a") -> n/a | G50: =IFERROR(INDEX(Features_Contents!$F:$F,MATCH($A50,Features_Contents!$A:$A,0)),"n/a") -> Include
A51: high_value_items | B51: policies_contents | C51: Declared high-value items | D51: Theft attractiveness, severity | E51: =IFERROR(INDEX(Features_Motor!$F:$F,MATCH($A51,Features_Motor!$A:$A,0)),"n/a") -> n/a | F51: =IFERROR(INDEX(Features_Buildings!$F:$F,MATCH($A51,Features_Buildings!$A:$A,0)),"n/a") -> n/a | G51: =IFERROR(INDEX(Features_Contents!$F:$F,MATCH($A51,Features_Contents!$A:$A,0)),"n/a") -> Include
A52: works_from_home | B52: policies_contents | C52: Someone works from home | D52: Daytime occupancy (theft), AD | E52: =IFERROR(INDEX(Features_Motor!$F:$F,MATCH($A52,Features_Motor!$A:$A,0)),"n/a") -> n/a | F52: =IFERROR(INDEX(Features_Buildings!$F:$F,MATCH($A52,Features_Buildings!$A:$A,0)),"n/a") -> n/a | G52: =IFERROR(INDEX(Features_Contents!$F:$F,MATCH($A52,Features_Contents!$A:$A,0)),"n/a") -> Test
A53: lodgers | B53: policies_contents | C53: Lodgers/students in household | D53: Theft, AD | E53: =IFERROR(INDEX(Features_Motor!$F:$F,MATCH($A53,Features_Motor!$A:$A,0)),"n/a") -> n/a | F53: =IFERROR(INDEX(Features_Buildings!$F:$F,MATCH($A53,Features_Buildings!$A:$A,0)),"n/a") -> n/a | G53: =IFERROR(INDEX(Features_Contents!$F:$F,MATCH($A53,Features_Contents!$A:$A,0)),"n/a") -> Test
A54: bicycle_cover | B54: policies_contents | C54: Optional bicycle cover | D54: Adds bicycle theft exposure | E54: =IFERROR(INDEX(Features_Motor!$F:$F,MATCH($A54,Features_Motor!$A:$A,0)),"n/a") -> n/a | F54: =IFERROR(INDEX(Features_Buildings!$F:$F,MATCH($A54,Features_Buildings!$A:$A,0)),"n/a") -> n/a | G54: =IFERROR(INDEX(Features_Contents!$F:$F,MATCH($A54,Features_Contents!$A:$A,0)),"n/a") -> Include
A55: voluntary_excess | B55: all policy files | C55: Customer-chosen excess 0/250/500/1000 | D55: Removes small claims; self-selection | E55: =IFERROR(INDEX(Features_Motor!$F:$F,MATCH($A55,Features_Motor!$A:$A,0)),"n/a") -> Include | F55: =IFERROR(INDEX(Features_Buildings!$F:$F,MATCH($A55,Features_Buildings!$A:$A,0)),"n/a") -> Include | G55: =IFERROR(INDEX(Features_Contents!$F:$F,MATCH($A55,Features_Contents!$A:$A,0)),"n/a") -> Include | H55: Claims already net of excess - do not subtract again
A56: compulsory_excess | B56: all policy files | C56: Insurer-set excess | D56: Removes small claims | E56: =IFERROR(INDEX(Features_Motor!$F:$F,MATCH($A56,Features_Motor!$A:$A,0)),"n/a") -> Include | F56: =IFERROR(INDEX(Features_Buildings!$F:$F,MATCH($A56,Features_Buildings!$A:$A,0)),"n/a") -> Include | G56: =IFERROR(INDEX(Features_Contents!$F:$F,MATCH($A56,Features_Contents!$A:$A,0)),"n/a") -> Include
A57: channel | B57: all policy files | C57: direct / comparison / broker | D57: Selection effect | E57: =IFERROR(INDEX(Features_Motor!$F:$F,MATCH($A57,Features_Motor!$A:$A,0)),"n/a") -> Test | F57: =IFERROR(INDEX(Features_Buildings!$F:$F,MATCH($A57,Features_Buildings!$A:$A,0)),"n/a") -> Test | G57: =IFERROR(INDEX(Features_Contents!$F:$F,MATCH($A57,Features_Contents!$A:$A,0)),"n/a") -> Test
A58: payment_method | B58: all policy files | C58: annual / monthly | D58: Financial-stress proxy | E58: =IFERROR(INDEX(Features_Motor!$F:$F,MATCH($A58,Features_Motor!$A:$A,0)),"n/a") -> Test | F58: =IFERROR(INDEX(Features_Buildings!$F:$F,MATCH($A58,Features_Buildings!$A:$A,0)),"n/a") -> Test | G58: =IFERROR(INDEX(Features_Contents!$F:$F,MATCH($A58,Features_Contents!$A:$A,0)),"n/a") -> Test | H58: Proxy factor - document in guardrails
A59: missed_payments_12m | B59: all policy files | C59: Missed payments last 12m | D59: Financial-stress proxy | E59: =IFERROR(INDEX(Features_Motor!$F:$F,MATCH($A59,Features_Motor!$A:$A,0)),"n/a") -> Test | F59: =IFERROR(INDEX(Features_Buildings!$F:$F,MATCH($A59,Features_Buildings!$A:$A,0)),"n/a") -> Test | G59: =IFERROR(INDEX(Features_Contents!$F:$F,MATCH($A59,Features_Contents!$A:$A,0)),"n/a") -> Test | H59: Proxy factor - document in guardrails
A60: new_business | B60: all policy files | C60: First year with insurer | D60: Selection / unknown risk | E60: =IFERROR(INDEX(Features_Motor!$F:$F,MATCH($A60,Features_Motor!$A:$A,0)),"n/a") -> Test | F60: =IFERROR(INDEX(Features_Buildings!$F:$F,MATCH($A60,Features_Buildings!$A:$A,0)),"n/a") -> Test | G60: =IFERROR(INDEX(Features_Contents!$F:$F,MATCH($A60,Features_Contents!$A:$A,0)),"n/a") -> Test
A61: renewal_count | B61: all policy files | C61: Previous renewals | D61: Tenure / survivorship | E61: =IFERROR(INDEX(Features_Motor!$F:$F,MATCH($A61,Features_Motor!$A:$A,0)),"n/a") -> Test | F61: =IFERROR(INDEX(Features_Buildings!$F:$F,MATCH($A61,Features_Buildings!$A:$A,0)),"n/a") -> Test | G61: =IFERROR(INDEX(Features_Contents!$F:$F,MATCH($A61,Features_Contents!$A:$A,0)),"n/a") -> Test | H61: Survivorship bias: lapsed customers absent from test
A62: days_quote_to_inception | B62: all policy files | C62: Days quote to start | D62: Anti-selection (last-minute buyers) | E62: =IFERROR(INDEX(Features_Motor!$F:$F,MATCH($A62,Features_Motor!$A:$A,0)),"n/a") -> Test | F62: =IFERROR(INDEX(Features_Buildings!$F:$F,MATCH($A62,Features_Buildings!$A:$A,0)),"n/a") -> Test | G62: =IFERROR(INDEX(Features_Contents!$F:$F,MATCH($A62,Features_Contents!$A:$A,0)),"n/a") -> Test
A63: discount_applied | B63: all policy files | C63: Discount on price | D63: Commercial decision, not risk | E63: =IFERROR(INDEX(Features_Motor!$F:$F,MATCH($A63,Features_Motor!$A:$A,0)),"n/a") -> Exclude | F63: =IFERROR(INDEX(Features_Buildings!$F:$F,MATCH($A63,Features_Buildings!$A:$A,0)),"n/a") -> Exclude | G63: =IFERROR(INDEX(Features_Contents!$F:$F,MATCH($A63,Features_Contents!$A:$A,0)),"n/a") -> Exclude | H63: Pricing decision - circular
A64: written_premium | B64: all policy files | C64: Premium under current pricing | D64: Current price = old risk model + loadings | E64: =IFERROR(INDEX(Features_Motor!$F:$F,MATCH($A64,Features_Motor!$A:$A,0)),"n/a") -> Exclude | F64: =IFERROR(INDEX(Features_Buildings!$F:$F,MATCH($A64,Features_Buildings!$A:$A,0)),"n/a") -> Exclude | G64: =IFERROR(INDEX(Features_Contents!$F:$F,MATCH($A64,Features_Contents!$A:$A,0)),"n/a") -> Exclude | H64: Circular for a technical price review; also embeds expense/profit loadings
A65: customer_service_contacts | B65: all policy files | C65: Service contacts | D65: LEAKAGE - rises after a claim | E65: =IFERROR(INDEX(Features_Motor!$F:$F,MATCH($A65,Features_Motor!$A:$A,0)),"n/a") -> n/a | F65: =IFERROR(INDEX(Features_Buildings!$F:$F,MATCH($A65,Features_Buildings!$A:$A,0)),"n/a") -> n/a | G65: =IFERROR(INDEX(Features_Contents!$F:$F,MATCH($A65,Features_Contents!$A:$A,0)),"n/a") -> n/a | H65: Excluded in 0_setup (leakage)
A66: occupation | B66: customers | C66: Occupation | D66: Lifestyle / use | E66: =IFERROR(INDEX(Features_Motor!$F:$F,MATCH($A66,Features_Motor!$A:$A,0)),"n/a") -> Test | F66: =IFERROR(INDEX(Features_Buildings!$F:$F,MATCH($A66,Features_Buildings!$A:$A,0)),"n/a") -> Exclude | G66: =IFERROR(INDEX(Features_Contents!$F:$F,MATCH($A66,Features_Contents!$A:$A,0)),"n/a") -> Exclude | H66: Potential proxy for protected traits - guardrail
A67: marital_status | B67: customers | C67: Marital status | D67: Driving behaviour proxy | E67: =IFERROR(INDEX(Features_Motor!$F:$F,MATCH($A67,Features_Motor!$A:$A,0)),"n/a") -> Test | F67: =IFERROR(INDEX(Features_Buildings!$F:$F,MATCH($A67,Features_Buildings!$A:$A,0)),"n/a") -> Exclude | G67: =IFERROR(INDEX(Features_Contents!$F:$F,MATCH($A67,Features_Contents!$A:$A,0)),"n/a") -> Exclude | H67: Sensitive in some markets - guardrail
A68: household_size | B68: customers | C68: People in household | D68: Occupancy, AD, EoW usage | E68: =IFERROR(INDEX(Features_Motor!$F:$F,MATCH($A68,Features_Motor!$A:$A,0)),"n/a") -> Exclude | F68: =IFERROR(INDEX(Features_Buildings!$F:$F,MATCH($A68,Features_Buildings!$A:$A,0)),"n/a") -> Test | G68: =IFERROR(INDEX(Features_Contents!$F:$F,MATCH($A68,Features_Contents!$A:$A,0)),"n/a") -> Test
A69: credit_band | B69: customers | C69: Credit band A-E | D69: Financial-stress / claims propensity | E69: =IFERROR(INDEX(Features_Motor!$F:$F,MATCH($A69,Features_Motor!$A:$A,0)),"n/a") -> Test | F69: =IFERROR(INDEX(Features_Buildings!$F:$F,MATCH($A69,Features_Buildings!$A:$A,0)),"n/a") -> Test | G69: =IFERROR(INDEX(Features_Contents!$F:$F,MATCH($A69,Features_Contents!$A:$A,0)),"n/a") -> Test | H69: Credit-based insurance scoring restricted in some markets - guardrail
A70: prior_claims_5y | B70: customers | C70: Declared claims 5y before joining | D70: Claims history | E70: =IFERROR(INDEX(Features_Motor!$F:$F,MATCH($A70,Features_Motor!$A:$A,0)),"n/a") -> Include | F70: =IFERROR(INDEX(Features_Buildings!$F:$F,MATCH($A70,Features_Buildings!$A:$A,0)),"n/a") -> Include | G70: =IFERROR(INDEX(Features_Contents!$F:$F,MATCH($A70,Features_Contents!$A:$A,0)),"n/a") -> Include
A71: licence_points | B71: customers | C71: Driving penalty points | D71: Driver conduct | E71: =IFERROR(INDEX(Features_Motor!$F:$F,MATCH($A71,Features_Motor!$A:$A,0)),"n/a") -> Include | F71: =IFERROR(INDEX(Features_Buildings!$F:$F,MATCH($A71,Features_Buildings!$A:$A,0)),"n/a") -> Exclude | G71: =IFERROR(INDEX(Features_Contents!$F:$F,MATCH($A71,Features_Contents!$A:$A,0)),"n/a") -> Exclude
A72: years_at_address | B72: customers | C72: Years at address | D72: Stability | E72: =IFERROR(INDEX(Features_Motor!$F:$F,MATCH($A72,Features_Motor!$A:$A,0)),"n/a") -> Test | F72: =IFERROR(INDEX(Features_Buildings!$F:$F,MATCH($A72,Features_Buildings!$A:$A,0)),"n/a") -> Test | G72: =IFERROR(INDEX(Features_Contents!$F:$F,MATCH($A72,Features_Contents!$A:$A,0)),"n/a") -> Test
A73: customer_since_year | B73: customers | C73: First policy year | D73: Calendar cohort | E73: =IFERROR(INDEX(Features_Motor!$F:$F,MATCH($A73,Features_Motor!$A:$A,0)),"n/a") -> Exclude | F73: =IFERROR(INDEX(Features_Buildings!$F:$F,MATCH($A73,Features_Buildings!$A:$A,0)),"n/a") -> Exclude | G73: =IFERROR(INDEX(Features_Contents!$F:$F,MATCH($A73,Features_Contents!$A:$A,0)),"n/a") -> Exclude | H73: Duplicates renewal_count; cohort year drifts out of range for 2025
A74: email_domain | B74: customers | C74: Anonymised email domain (~20% each) | D74: None - noise | E74: =IFERROR(INDEX(Features_Motor!$F:$F,MATCH($A74,Features_Motor!$A:$A,0)),"n/a") -> Exclude | F74: =IFERROR(INDEX(Features_Buildings!$F:$F,MATCH($A74,Features_Buildings!$A:$A,0)),"n/a") -> Exclude | G74: =IFERROR(INDEX(Features_Contents!$F:$F,MATCH($A74,Features_Contents!$A:$A,0)),"n/a") -> Exclude | H74: Uniform; no causal path
A75: marketing_consent | B75: customers | C75: Marketing consent | D75: None | E75: =IFERROR(INDEX(Features_Motor!$F:$F,MATCH($A75,Features_Motor!$A:$A,0)),"n/a") -> Exclude | F75: =IFERROR(INDEX(Features_Buildings!$F:$F,MATCH($A75,Features_Buildings!$A:$A,0)),"n/a") -> Exclude | G75: =IFERROR(INDEX(Features_Contents!$F:$F,MATCH($A75,Features_Contents!$A:$A,0)),"n/a") -> Exclude | H75: No causal path
A76: document_preference | B76: customers | C76: email / post / app | D76: None (age proxy at best) | E76: =IFERROR(INDEX(Features_Motor!$F:$F,MATCH($A76,Features_Motor!$A:$A,0)),"n/a") -> Exclude | F76: =IFERROR(INDEX(Features_Buildings!$F:$F,MATCH($A76,Features_Buildings!$A:$A,0)),"n/a") -> Exclude | G76: =IFERROR(INDEX(Features_Contents!$F:$F,MATCH($A76,Features_Contents!$A:$A,0)),"n/a") -> Exclude | H76: Proxy only
A77: previous_insurer | B77: customers | C77: Previous insurer | D77: Weak selection signal | E77: =IFERROR(INDEX(Features_Motor!$F:$F,MATCH($A77,Features_Motor!$A:$A,0)),"n/a") -> Exclude | F77: =IFERROR(INDEX(Features_Buildings!$F:$F,MATCH($A77,Features_Buildings!$A:$A,0)),"n/a") -> Exclude | G77: =IFERROR(INDEX(Features_Contents!$F:$F,MATCH($A77,Features_Contents!$A:$A,0)),"n/a") -> Exclude | H77: Showed spurious top-10 importance for fire / subsidence in WENDY 3
A78: campaign_code | B78: customers | C78: Acquisition campaign | D78: Marketing | E78: =IFERROR(INDEX(Features_Motor!$F:$F,MATCH($A78,Features_Motor!$A:$A,0)),"n/a") -> Exclude | F78: =IFERROR(INDEX(Features_Buildings!$F:$F,MATCH($A78,Features_Buildings!$A:$A,0)),"n/a") -> Exclude | G78: =IFERROR(INDEX(Features_Contents!$F:$F,MATCH($A78,Features_Contents!$A:$A,0)),"n/a") -> Exclude | H78: No causal path; null = no campaign
A79: branch_id | B79: customers | C79: Servicing branch | D79: Geography proxy (region already used) | E79: =IFERROR(INDEX(Features_Motor!$F:$F,MATCH($A79,Features_Motor!$A:$A,0)),"n/a") -> Exclude | F79: =IFERROR(INDEX(Features_Buildings!$F:$F,MATCH($A79,Features_Buildings!$A:$A,0)),"n/a") -> Exclude | G79: =IFERROR(INDEX(Features_Contents!$F:$F,MATCH($A79,Features_Contents!$A:$A,0)),"n/a") -> Exclude | H79: Duplicates geography
A80: marketing_segment | B80: customers | C80: Marketing segment | D80: Opaque derived score | E80: =IFERROR(INDEX(Features_Motor!$F:$F,MATCH($A80,Features_Motor!$A:$A,0)),"n/a") -> Exclude | F80: =IFERROR(INDEX(Features_Buildings!$F:$F,MATCH($A80,Features_Buildings!$A:$A,0)),"n/a") -> Exclude | G80: =IFERROR(INDEX(Features_Contents!$F:$F,MATCH($A80,Features_Contents!$A:$A,0)),"n/a") -> Exclude | H80: Unknown construction - could encode price or protected traits
A81: region | B81: addresses | C81: Region R01-R12 | D81: Geography | E81: =IFERROR(INDEX(Features_Motor!$F:$F,MATCH($A81,Features_Motor!$A:$A,0)),"n/a") -> Include | F81: =IFERROR(INDEX(Features_Buildings!$F:$F,MATCH($A81,Features_Buildings!$A:$A,0)),"n/a") -> Include | G81: =IFERROR(INDEX(Features_Contents!$F:$F,MATCH($A81,Features_Contents!$A:$A,0)),"n/a") -> Include
A82: urban_density | B82: addresses | C82: rural ... dense_urban | D82: Traffic, crime density | E82: =IFERROR(INDEX(Features_Motor!$F:$F,MATCH($A82,Features_Motor!$A:$A,0)),"n/a") -> Include | F82: =IFERROR(INDEX(Features_Buildings!$F:$F,MATCH($A82,Features_Buildings!$A:$A,0)),"n/a") -> Test | G82: =IFERROR(INDEX(Features_Contents!$F:$F,MATCH($A82,Features_Contents!$A:$A,0)),"n/a") -> Include
A83: flood_zone | B83: addresses | C83: Flood zone 1-5 | D83: Flood hazard | E83: =IFERROR(INDEX(Features_Motor!$F:$F,MATCH($A83,Features_Motor!$A:$A,0)),"n/a") -> Exclude | F83: =IFERROR(INDEX(Features_Buildings!$F:$F,MATCH($A83,Features_Buildings!$A:$A,0)),"n/a") -> Include | G83: =IFERROR(INDEX(Features_Contents!$F:$F,MATCH($A83,Features_Contents!$A:$A,0)),"n/a") -> Include
A84: distance_to_river_km | B84: addresses | C84: Distance to river | D84: Flood hazard | E84: =IFERROR(INDEX(Features_Motor!$F:$F,MATCH($A84,Features_Motor!$A:$A,0)),"n/a") -> Exclude | F84: =IFERROR(INDEX(Features_Buildings!$F:$F,MATCH($A84,Features_Buildings!$A:$A,0)),"n/a") -> Include | G84: =IFERROR(INDEX(Features_Contents!$F:$F,MATCH($A84,Features_Contents!$A:$A,0)),"n/a") -> Include
A85: elevation_m | B85: addresses | C85: Height above river level | D85: Flood hazard | E85: =IFERROR(INDEX(Features_Motor!$F:$F,MATCH($A85,Features_Motor!$A:$A,0)),"n/a") -> Exclude | F85: =IFERROR(INDEX(Features_Buildings!$F:$F,MATCH($A85,Features_Buildings!$A:$A,0)),"n/a") -> Include | G85: =IFERROR(INDEX(Features_Contents!$F:$F,MATCH($A85,Features_Contents!$A:$A,0)),"n/a") -> Include
A86: soil_type | B86: addresses | C86: clay/sand/loam/chalk/rock | D86: Subsidence hazard (clay shrink-swell) | E86: =IFERROR(INDEX(Features_Motor!$F:$F,MATCH($A86,Features_Motor!$A:$A,0)),"n/a") -> Exclude | F86: =IFERROR(INDEX(Features_Buildings!$F:$F,MATCH($A86,Features_Buildings!$A:$A,0)),"n/a") -> Include | G86: =IFERROR(INDEX(Features_Contents!$F:$F,MATCH($A86,Features_Contents!$A:$A,0)),"n/a") -> Exclude
A87: year_built | B87: addresses | C87: Year built | D87: Plumbing age, construction standard | E87: =IFERROR(INDEX(Features_Motor!$F:$F,MATCH($A87,Features_Motor!$A:$A,0)),"n/a") -> Exclude | F87: =IFERROR(INDEX(Features_Buildings!$F:$F,MATCH($A87,Features_Buildings!$A:$A,0)),"n/a") -> Include | G87: =IFERROR(INDEX(Features_Contents!$F:$F,MATCH($A87,Features_Contents!$A:$A,0)),"n/a") -> Include
A88: property_type | B88: addresses | C88: detached/semi/terraced/flat | D88: Exposure, flood floor level | E88: =IFERROR(INDEX(Features_Motor!$F:$F,MATCH($A88,Features_Motor!$A:$A,0)),"n/a") -> Exclude | F88: =IFERROR(INDEX(Features_Buildings!$F:$F,MATCH($A88,Features_Buildings!$A:$A,0)),"n/a") -> Include | G88: =IFERROR(INDEX(Features_Contents!$F:$F,MATCH($A88,Features_Contents!$A:$A,0)),"n/a") -> Include
A89: roof_type | B89: addresses | C89: pitched / flat | D89: Storm and water ingress | E89: =IFERROR(INDEX(Features_Motor!$F:$F,MATCH($A89,Features_Motor!$A:$A,0)),"n/a") -> Exclude | F89: =IFERROR(INDEX(Features_Buildings!$F:$F,MATCH($A89,Features_Buildings!$A:$A,0)),"n/a") -> Include | G89: =IFERROR(INDEX(Features_Contents!$F:$F,MATCH($A89,Features_Contents!$A:$A,0)),"n/a") -> Test
A90: basement | B90: addresses | C90: Basement | D90: Flood / EoW / subsidence | E90: =IFERROR(INDEX(Features_Motor!$F:$F,MATCH($A90,Features_Motor!$A:$A,0)),"n/a") -> Exclude | F90: =IFERROR(INDEX(Features_Buildings!$F:$F,MATCH($A90,Features_Buildings!$A:$A,0)),"n/a") -> Include | G90: =IFERROR(INDEX(Features_Contents!$F:$F,MATCH($A90,Features_Contents!$A:$A,0)),"n/a") -> Include
A91: trees_within_5m | B91: addresses | C91: Trees within 5m | D91: Subsidence (root shrinkage), storm debris | E91: =IFERROR(INDEX(Features_Motor!$F:$F,MATCH($A91,Features_Motor!$A:$A,0)),"n/a") -> Exclude | F91: =IFERROR(INDEX(Features_Buildings!$F:$F,MATCH($A91,Features_Buildings!$A:$A,0)),"n/a") -> Include | G91: =IFERROR(INDEX(Features_Contents!$F:$F,MATCH($A91,Features_Contents!$A:$A,0)),"n/a") -> Exclude
A92: listed_building | B92: addresses | C92: Listed building | D92: Rebuild cost (severity) | E92: =IFERROR(INDEX(Features_Motor!$F:$F,MATCH($A92,Features_Motor!$A:$A,0)),"n/a") -> Exclude | F92: =IFERROR(INDEX(Features_Buildings!$F:$F,MATCH($A92,Features_Buildings!$A:$A,0)),"n/a") -> Include | G92: =IFERROR(INDEX(Features_Contents!$F:$F,MATCH($A92,Features_Contents!$A:$A,0)),"n/a") -> Exclude
A93: bedrooms | B93: addresses | C93: Bedrooms | D93: Size / severity | E93: =IFERROR(INDEX(Features_Motor!$F:$F,MATCH($A93,Features_Motor!$A:$A,0)),"n/a") -> Exclude | F93: =IFERROR(INDEX(Features_Buildings!$F:$F,MATCH($A93,Features_Buildings!$A:$A,0)),"n/a") -> Include | G93: =IFERROR(INDEX(Features_Contents!$F:$F,MATCH($A93,Features_Contents!$A:$A,0)),"n/a") -> Test
A94: energy_rating | B94: addresses | C94: Energy rating A-G | D94: Building age / heating proxy | E94: =IFERROR(INDEX(Features_Motor!$F:$F,MATCH($A94,Features_Motor!$A:$A,0)),"n/a") -> Exclude | F94: =IFERROR(INDEX(Features_Buildings!$F:$F,MATCH($A94,Features_Buildings!$A:$A,0)),"n/a") -> Test | G94: =IFERROR(INDEX(Features_Contents!$F:$F,MATCH($A94,Features_Contents!$A:$A,0)),"n/a") -> Exclude | H94: Proxy - keep only where it validates
A95: solar_panels | B95: addresses | C95: Solar panels | D95: Electrical fire, roof damage | E95: =IFERROR(INDEX(Features_Motor!$F:$F,MATCH($A95,Features_Motor!$A:$A,0)),"n/a") -> Exclude | F95: =IFERROR(INDEX(Features_Buildings!$F:$F,MATCH($A95,Features_Buildings!$A:$A,0)),"n/a") -> Test | G95: =IFERROR(INDEX(Features_Contents!$F:$F,MATCH($A95,Features_Contents!$A:$A,0)),"n/a") -> Exclude
A96: hail_days | B96: weather (policy year) | C96: Hail days in year | D96: Hail hazard | E96: =IFERROR(INDEX(Features_Motor!$F:$F,MATCH($A96,Features_Motor!$A:$A,0)),"n/a") -> Include | F96: =IFERROR(INDEX(Features_Buildings!$F:$F,MATCH($A96,Features_Buildings!$A:$A,0)),"n/a") -> Test | G96: =IFERROR(INDEX(Features_Contents!$F:$F,MATCH($A96,Features_Contents!$A:$A,0)),"n/a") -> Exclude | H96: Realised weather of the row's year (2025 supplied for test)
A97: wind_exposure_index | B97: weather (policy year) | C97: Wind exposure 0-10 | D97: Storm hazard | E97: =IFERROR(INDEX(Features_Motor!$F:$F,MATCH($A97,Features_Motor!$A:$A,0)),"n/a") -> Test | F97: =IFERROR(INDEX(Features_Buildings!$F:$F,MATCH($A97,Features_Buildings!$A:$A,0)),"n/a") -> Include | G97: =IFERROR(INDEX(Features_Contents!$F:$F,MATCH($A97,Features_Contents!$A:$A,0)),"n/a") -> Exclude | H97: Realised weather
A98: freezing_days | B98: weather (policy year) | C98: Days below freezing | D98: Burst pipes, icy roads | E98: =IFERROR(INDEX(Features_Motor!$F:$F,MATCH($A98,Features_Motor!$A:$A,0)),"n/a") -> Test | F98: =IFERROR(INDEX(Features_Buildings!$F:$F,MATCH($A98,Features_Buildings!$A:$A,0)),"n/a") -> Include | G98: =IFERROR(INDEX(Features_Contents!$F:$F,MATCH($A98,Features_Contents!$A:$A,0)),"n/a") -> Include | H98: Realised weather
A99: dry_summer_index | B99: weather (policy year) | C99: Dry summer 0-1 | D99: Clay shrinkage (subsidence), fire | E99: =IFERROR(INDEX(Features_Motor!$F:$F,MATCH($A99,Features_Motor!$A:$A,0)),"n/a") -> Exclude | F99: =IFERROR(INDEX(Features_Buildings!$F:$F,MATCH($A99,Features_Buildings!$A:$A,0)),"n/a") -> Include | G99: =IFERROR(INDEX(Features_Contents!$F:$F,MATCH($A99,Features_Contents!$A:$A,0)),"n/a") -> Exclude | H99: Realised weather
A100: wildfire_index | B100: weather (policy year) | C100: Wildfire 0-1 | D100: Fire hazard | E100: =IFERROR(INDEX(Features_Motor!$F:$F,MATCH($A100,Features_Motor!$A:$A,0)),"n/a") -> Exclude | F100: =IFERROR(INDEX(Features_Buildings!$F:$F,MATCH($A100,Features_Buildings!$A:$A,0)),"n/a") -> Include | G100: =IFERROR(INDEX(Features_Contents!$F:$F,MATCH($A100,Features_Contents!$A:$A,0)),"n/a") -> Exclude | H100: Realised weather
A101: rainfall_mm | B101: weather (policy year) | C101: Annual rainfall | D101: Flood, storm ingress, wet roads | E101: =IFERROR(INDEX(Features_Motor!$F:$F,MATCH($A101,Features_Motor!$A:$A,0)),"n/a") -> Test | F101: =IFERROR(INDEX(Features_Buildings!$F:$F,MATCH($A101,Features_Buildings!$A:$A,0)),"n/a") -> Include | G101: =IFERROR(INDEX(Features_Contents!$F:$F,MATCH($A101,Features_Contents!$A:$A,0)),"n/a") -> Include | H101: Realised weather
A102: mean_temperature_c | B102: weather (policy year) | C102: Mean temperature | D102: Freeze / drought conditions | E102: =IFERROR(INDEX(Features_Motor!$F:$F,MATCH($A102,Features_Motor!$A:$A,0)),"n/a") -> Exclude | F102: =IFERROR(INDEX(Features_Buildings!$F:$F,MATCH($A102,Features_Buildings!$A:$A,0)),"n/a") -> Test | G102: =IFERROR(INDEX(Features_Contents!$F:$F,MATCH($A102,Features_Contents!$A:$A,0)),"n/a") -> Test | H102: Realised weather
A103: customer_age | B103: derived (2_clean) | C103: Customer age at row start | D103: Duplicates driver_age / policyholder_age | E103: =IFERROR(INDEX(Features_Motor!$F:$F,MATCH($A103,Features_Motor!$A:$A,0)),"n/a") -> Exclude | F103: =IFERROR(INDEX(Features_Buildings!$F:$F,MATCH($A103,Features_Buildings!$A:$A,0)),"n/a") -> Exclude | G103: =IFERROR(INDEX(Features_Contents!$F:$F,MATCH($A103,Features_Contents!$A:$A,0)),"n/a") -> Exclude
A104: start_month | B104: derived (2_clean) | C104: Row start month | D104: Seasonality of partial-year rows | E104: =IFERROR(INDEX(Features_Motor!$F:$F,MATCH($A104,Features_Motor!$A:$A,0)),"n/a") -> Test | F104: =IFERROR(INDEX(Features_Buildings!$F:$F,MATCH($A104,Features_Buildings!$A:$A,0)),"n/a") -> Test | G104: =IFERROR(INDEX(Features_Contents!$F:$F,MATCH($A104,Features_Contents!$A:$A,0)),"n/a") -> Test
A105: years_with_insurer | B105: derived (2_clean) | C105: policy_year - customer_since_year | D105: Duplicates renewal_count | E105: =IFERROR(INDEX(Features_Motor!$F:$F,MATCH($A105,Features_Motor!$A:$A,0)),"n/a") -> Exclude | F105: =IFERROR(INDEX(Features_Buildings!$F:$F,MATCH($A105,Features_Buildings!$A:$A,0)),"n/a") -> Exclude | G105: =IFERROR(INDEX(Features_Contents!$F:$F,MATCH($A105,Features_Contents!$A:$A,0)),"n/a") -> Exclude
A106: hist_policy_claims_prev | B106: derived (this script) | C106: Positive claims on this policy with loss in prior year AND reported by end of prior year; NA if no prior-year row or year 2021 | D106: Own experience rating (renewal knowledge) | E106: =IFERROR(INDEX(Features_Motor!$F:$F,MATCH($A106,Features_Motor!$A:$A,0)),"n/a") -> Include | F106: =IFERROR(INDEX(Features_Buildings!$F:$F,MATCH($A106,Features_Buildings!$A:$A,0)),"n/a") -> Include | G106: =IFERROR(INDEX(Features_Contents!$F:$F,MATCH($A106,Features_Contents!$A:$A,0)),"n/a") -> Include | H106: Built only from info known at renewal - no leakage
A107: hist_customer_claims_other_lines_prev | B107: derived (this script) | C107: Same customer's positive claims on the OTHER two lines, prior year, reported by its end; NA for 2021 | D107: Cross-line behaviour | E107: =IFERROR(INDEX(Features_Motor!$F:$F,MATCH($A107,Features_Motor!$A:$A,0)),"n/a") -> Test | F107: =IFERROR(INDEX(Features_Buildings!$F:$F,MATCH($A107,Features_Buildings!$A:$A,0)),"n/a") -> Test | G107: =IFERROR(INDEX(Features_Contents!$F:$F,MATCH($A107,Features_Contents!$A:$A,0)),"n/a") -> Test | H107: Built only from info known at renewal

Sheet Method_Mix
A1: line | B1: peril | C1: method | D1: wendy04_method | E1: reason
A2: buildings | B2: accidental_damage | C2: freq_sev | D2: freq_sev | E2: WENDY 4 pick (mean developed D2 over 2023-24)
A3: buildings | B3: escape_of_water | C3: freq_sev | D3: freq_sev | E3: WENDY 4 pick (mean developed D2 over 2023-24)
A4: buildings | B4: fire | C4: freq_sev | D4: freq_sev | E4: WENDY 4 pick (mean developed D2 over 2023-24)
A5: buildings | B5: flood | C5: freq_sev | D5: freq_sev | E5: WENDY 4 pick (mean developed D2 over 2023-24)
A6: buildings | B6: storm | C6: freq_sev | D6: freq_sev | E6: WENDY 4 pick (mean developed D2 over 2023-24)
A7: buildings | B7: subsidence | C7: freq_sev | D7: freq_sev | E7: WENDY 4 pick (mean developed D2 over 2023-24)
A8: contents | B8: accidental_damage | C8: freq_sev | D8: freq_sev | E8: WENDY 4 pick (mean developed D2 over 2023-24)
A9: contents | B9: escape_of_water | C9: tweedie | D9: tweedie | E9: WENDY 4 pick (mean developed D2 over 2023-24)
A10: contents | B10: flood | C10: freq_sev | D10: freq_sev | E10: WENDY 4 pick (mean developed D2 over 2023-24)
A11: contents | B11: theft | C11: freq_sev | D11: freq_sev | E11: WENDY 4 pick (mean developed D2 over 2023-24)
A12: motor | B12: bodily_injury | C12: tweedie | D12: tweedie | E12: WENDY 4 pick (mean developed D2 over 2023-24)
... A16: motor | B16: third_party_prop | C16: freq_sev | D16: freq_sev | E16: WENDY 4 pick (mean developed D2 over 2023-24)

Sheet Changes_vs_WENDY4
A1: area | B1: line | C1: peril | D1: item | E1: wendy04_value | F1: this_model | G1: reason_and_evidence
A2: Features | B2: motor | C2: third_party_prop | D2: voluntary_excess | E2: F | F2: B | G2: Excess removes small claims and slices every claim: frequency and severity of every peril (B6: ALL +0.0010, 100% of bootstrap draws; BI Tweedie +0.0055, fire +0.0053, flood +0.002).
A3: Features | B3: motor | C3: bodily_injury | D3: voluntary_excess | E3: - | F3: B | G3: Excess removes small claims and slices every claim: frequency and severity of every peril (B6: ALL +0.0010, 100% of bootstrap draws; BI Tweedie +0.0055, fire +0.0053, flood +0.002).
A4: Features | B4: buildings | C4: storm | D4: voluntary_excess | E4: F | F4: B | G4: Excess removes small claims and slices every claim: frequency and severity of every peril (B6: ALL +0.0010, 100% of bootstrap draws; BI Tweedie +0.0055, fire +0.0053, flood +0.002).
A5: Features | B5: buildings | C5: flood | D5: voluntary_excess | E5: F | F5: B | G5: Excess removes small claims and slices every claim: frequency and severity of every peril (B6: ALL +0.0010, 100% of bootstrap draws; BI Tweedie +0.0055, fire +0.0053, flood +0.002).
A6: Features | B6: buildings | C6: subsidence | D6: voluntary_excess | E6: F | F6: B | G6: Excess removes small claims and slices every claim: frequency and severity of every peril (B6: ALL +0.0010, 100% of bootstrap draws; BI Tweedie +0.0055, fire +0.0053, flood +0.002).
A7: Features | B7: buildings | C7: fire | D7: voluntary_excess | E7: S | F7: B | G7: Excess removes small claims and slices every claim: frequency and severity of every peril (B6: ALL +0.0010, 100% of bootstrap draws; BI Tweedie +0.0055, fire +0.0053, flood +0.002).
A8: Features | B8: contents | C8: flood | D8: voluntary_excess | E8: F | F8: B | G8: Excess removes small claims and slices every claim: frequency and severity of every peril (B6: ALL +0.0010, 100% of bootstrap draws; BI Tweedie +0.0055, fire +0.0053, flood +0.002).
A9: Features | B9: buildings | C9: flood | D9: days_quote_to_inception | E9: F | F9: - | G9: Peril lab: admin fields have no flood mechanism; drop gained +0.00005 (2023 0.00000 / 2024 +0.00010 / 2022 -0.00008).
A10: Features | B10: buildings | C10: flood | D10: start_month | E10: F | F10: - | G10: Dropped together with days_quote_to_inception (lab variant drop_admin).
A11: Features | B11: motor | C11: third_party_prop | D11: freezing_days | E11: F | F11: - | G11: Peril lab: realised weather adds noise to third-party property; drop gained +0.00036 (2023 +0.00064 / 2024 +0.00008 / 2022 +0.00012).
A12: Features | B12: motor | C12: third_party_prop | D12: rainfall_mm | E12: F | F12: - | G12: Dropped together with freezing_days (lab variant drop_weather).
... A23: Method_Mix | B23: motor | C23: own_damage | D23: method | E23: tweedie | F23: freq_sev | G23: Peril lab: freq_sev beats Tweedie by +0.0005 ALL (2023 +0.00059 / 2024 +0.00043 / 2022 +0.00001)

Sheet Final_Features
A1: line | B1: peril | C1: method | D1: feature | E1: code | F1: part | G1: mono_freq | H1: mono_sev | I1: used_by_method
A2: buildings | B2: accidental_damage | C2: freq_sev | D2: compulsory_excess | E2: S | F2: severity only | G2: 0 | H2: 0 | I2: freq x sev: F/B in frequency, S/B in severity
A3: buildings | B3: accidental_damage | C3: freq_sev | D3: sum_insured | E3: S | F3: severity only | G3: 0 | H3: 1 | I3: freq x sev: F/B in frequency, S/B in severity
A4: buildings | B4: accidental_damage | C4: freq_sev | D4: bedrooms | E4: F | F4: frequency only | G4: 0 | H4: 0 | I4: freq x sev: F/B in frequency, S/B in severity
A5: buildings | B5: accidental_damage | C5: freq_sev | D5: channel | E5: F | F5: frequency only | G5: 0 | H5: 0 | I5: freq x sev: F/B in frequency, S/B in severity
A6: buildings | B6: accidental_damage | C6: freq_sev | D6: credit_band | E6: F | F6: frequency only | G6: 0 | H6: 0 | I6: freq x sev: F/B in frequency, S/B in severity
A7: buildings | B7: accidental_damage | C7: freq_sev | D7: days_quote_to_inception | E7: F | F7: frequency only | G7: 0 | H7: 0 | I7: freq x sev: F/B in frequency, S/B in severity
A8: buildings | B8: accidental_damage | C8: freq_sev | D8: hist_customer_claims_other_lines_prev | E8: F | F8: frequency only | G8: 1 | H8: 0 | I8: freq x sev: F/B in frequency, S/B in severity
A9: buildings | B9: accidental_damage | C9: freq_sev | D9: hist_policy_claims_prev | E9: F | F9: frequency only | G9: 1 | H9: 0 | I9: freq x sev: F/B in frequency, S/B in severity
A10: buildings | B10: accidental_damage | C10: freq_sev | D10: household_size | E10: F | F10: frequency only | G10: 0 | H10: 0 | I10: freq x sev: F/B in frequency, S/B in severity
A11: buildings | B11: accidental_damage | C11: freq_sev | D11: missed_payments_12m | E11: F | F11: frequency only | G11: 1 | H11: 0 | I11: freq x sev: F/B in frequency, S/B in severity
A12: buildings | B12: accidental_damage | C12: freq_sev | D12: new_business | E12: F | F12: frequency only | G12: 0 | H12: 0 | I12: freq x sev: F/B in frequency, S/B in severity
A13: buildings | B13: accidental_damage | C13: freq_sev | D13: occupancy | E13: F | F13: frequency only | G13: 0 | H13: 0 | I13: freq x sev: F/B in frequency, S/B in severity
... A349: motor | B349: third_party_prop | C349: freq_sev | D349: voluntary_excess | E349: B | F349: frequency + severity | G349: -1 | H349: 0 | I349: freq x sev: F/B in frequency, S/B in severity

Sheet Feature_Matrix
A1: line | B1: feature | C1: buildings accidental_damage | D1: buildings escape_of_water | E1: buildings fire | F1: buildings flood | G1: buildings storm | H1: buildings subsidence | I1: contents accidental_damage | J1: contents escape_of_water | K1: contents flood | L1: contents theft | M1: motor bodily_injury | N1: motor glass_hail | O1: motor own_damage | P1: motor theft | Q1: motor third_party_prop
A2: buildings | B2: accidental_damage_cover | C2: B | D2: - | E2: - | F2: - | G2: - | H2: - | I2: - | J2: - | K2: - | L2: - | M2: - | N2: - | O2: - | P2: - | Q2: -
A3: buildings | B3: basement | C3: - | D3: F | E3: - | F3: B | G3: - | H3: F | I3: - | J3: - | K3: - | L3: - | M3: - | N3: - | O3: - | P3: - | Q3: -
A4: buildings | B4: bedrooms | C4: F | D4: S | E4: S | F4: S | G4: S | H4: S | I4: - | J4: - | K4: - | L4: - | M4: - | N4: - | O4: - | P4: - | Q4: -
A5: buildings | B5: channel | C5: F | D5: F | E5: - | F5: - | G5: F | H5: - | I5: - | J5: - | K5: - | L5: - | M5: - | N5: - | O5: - | P5: - | Q5: -
A6: buildings | B6: compulsory_excess | C6: S | D6: S | E6: S | F6: S | G6: S | H6: S | I6: - | J6: - | K6: - | L6: - | M6: - | N6: - | O6: - | P6: - | Q6: -
A7: buildings | B7: construction_type | C7: - | D7: F | E7: B | F7: - | G7: B | H7: B | I7: - | J7: - | K7: - | L7: - | M7: - | N7: - | O7: - | P7: - | Q7: -
A8: buildings | B8: credit_band | C8: F | D8: F | E8: F | F8: - | G8: - | H8: - | I8: - | J8: - | K8: - | L8: - | M8: - | N8: - | O8: - | P8: - | Q8: -
A9: buildings | B9: days_quote_to_inception | C9: F | D9: F | E9: - | F9: - | G9: F | H9: - | I9: - | J9: - | K9: - | L9: - | M9: - | N9: - | O9: - | P9: - | Q9: -
A10: buildings | B10: days_unoccupied | C10: - | D10: B | E10: F | F10: - | G10: - | H10: - | I10: - | J10: - | K10: - | L10: - | M10: - | N10: - | O10: - | P10: - | Q10: -
A11: buildings | B11: distance_to_river_km | C11: - | D11: - | E11: - | F11: B | G11: - | H11: - | I11: - | J11: - | K11: - | L11: - | M11: - | N11: - | O11: - | P11: - | Q11: -
A12: buildings | B12: dry_summer_index | C12: - | D12: - | E12: F | F12: - | G12: - | H12: B | I12: - | J12: - | K12: - | L12: - | M12: - | N12: - | O12: - | P12: - | Q12: -
... A124: motor | B124: years_licensed | C124: - | D124: - | E124: - | F124: - | G124: - | H124: - | I124: - | J124: - | K124: - | L124: - | M124: F | N124: - | O124: F | P124: - | Q124: F

Sheet IBNR_Chain_Ladder
A1: line | B1: peril | C1: policy_year | D1: exposure | E1: reported_share_wendy4 | F1: reported_share_this_model | G1: ibnr_factor | H1: ratio_to_wendy4
A2: motor | B2: own_damage | C2: 2021 | D2: 187991.54 | E2: 1 | F2: 1 | G2: 1 | H2: 1
A3: motor | B3: own_damage | C3: 2022 | D3: 199698.5 | E3: 1 | F3: 1 | G3: 1 | H3: 1
A4: motor | B4: own_damage | C4: 2023 | D4: 199681.85 | E4: 0.99979802 | F4: 0.99899939 | G4: 1.0010016 | H4: 0.9992012
A5: motor | B5: own_damage | C5: 2024 | D5: 199785.63 | E5: 0.99577726 | F5: 0.96781073 | G5: 1.0332599 | H5: 0.97191487
A6: motor | B6: third_party_prop | C6: 2021 | D6: 187991.54 | E6: 1 | F6: 1 | G6: 1 | H6: 1
A7: motor | B7: third_party_prop | C7: 2022 | D7: 199698.5 | E7: 1 | F7: 1 | G7: 1 | H7: 1
A8: motor | B8: third_party_prop | C8: 2023 | D8: 199681.85 | E8: 0.99931925 | F8: 0.99856859 | G8: 1.0014335 | H8: 0.99924882
A9: motor | B9: third_party_prop | C9: 2024 | D9: 199785.63 | E9: 0.99237279 | F9: 0.93860576 | G9: 1.06541 | H9: 0.94581973
A10: motor | B10: bodily_injury | C10: 2021 | D10: 187991.54 | E10: 0.99974865 | F10: 0.99818424 | G10: 1.0018191 | H10: 0.9984352
A11: motor | B11: bodily_injury | C11: 2022 | D11: 199698.5 | E11: 0.99599284 | F11: 0.99091388 | G11: 1.0091694 | H11: 0.9949006
A12: motor | B12: bodily_injury | C12: 2023 | D12: 199681.85 | E12: 0.95361734 | F12: 0.94033723 | G12: 1.0634483 | H12: 0.98607397
A13: motor | B13: bodily_injury | C13: 2024 | D13: 199785.63 | E13: 0.62551736 | F13: 0.56227356 | G13: 1.7784937 | H13: 0.89889361
... A61: contents | B61: flood | C61: 2024 | D61: 149966.76 | E61: 0.98932186 | F61: 0.96382378 | G61: 1.0375341 | H61: 0.97422671

Sheet CL_Triangle_Factors
A1: line | B1: peril | C1: loss_quarter | D1: dev_quarter_latest | E1: reported | F1: cdf_to_ult | G1: share | H1: dev_k | I1: age_to_age_k_to_k1
A2: motor | B2: own_damage | C2: 44197 | D2: 15 | E2: 2778 | F2: 1 | G2: 1 | H2: 0 | I2: 1.1312014
A3: motor | B3: own_damage | C3: 44287 | D3: 14 | E3: 2875 | F3: 1 | G3: 1 | H3: 1 | I3: 1.0000236
A4: motor | B4: own_damage | C4: 44378 | D4: 13 | E4: 3055 | F4: 1 | G4: 1 | H4: 2 | I4: 1
A5: motor | B5: own_damage | C5: 44470 | D5: 12 | E5: 3272 | F5: 1 | G5: 1 | H5: 3 | I5: 1.0002731
A6: motor | B6: own_damage | C6: 44562 | D6: 11 | E6: 3139 | F6: 1 | G6: 1 | H6: 4 | I6: 1.0021478
A7: motor | B7: own_damage | C7: 44652 | D7: 10 | E7: 3210 | F7: 1 | G7: 1 | H7: 5 | I7: 1.0009153
A8: motor | B8: own_damage | C8: 44743 | D8: 9 | E8: 3165 | F8: 1 | G8: 1 | H8: 6 | I8: 1
A9: motor | B9: own_damage | C9: 44835 | D9: 8 | E9: 3357 | F9: 1 | G9: 1 | H9: 7 | I9: 1
A10: motor | B10: own_damage | C10: 44927 | D10: 7 | E10: 2864 | F10: 1 | G10: 1 | H10: 8 | I10: 1
A11: motor | B11: own_damage | C11: 45017 | D11: 6 | E11: 2903 | F11: 1 | G11: 1 | H11: 9 | I11: 1
A12: motor | B12: own_damage | C12: 45108 | D12: 5 | E12: 3004 | F12: 1.0009153 | G12: 0.99908551 | H12: 10 | I12: 1
A13: motor | B13: own_damage | C13: 45200 | D13: 4 | E13: 3099 | F13: 1.0030651 | G13: 0.99694423 | H13: 11 | I13: 1
... A16: motor | B16: own_damage | C16: 45474 | D16: 1 | E16: 3036 | F16: 1.0033628 | G16: 0.99664848 | H16: 14 | I16: 1
A17: motor | B17: own_damage | C17: 45566 | D17: 0 | E17: 2727 | F17: 1.1350054 | G17: 0.88105305 | H17: 15
A18: motor | B18: third_party_prop | C18: 44197 | D18: 15 | E18: 1826 | F18: 1 | G18: 1 | H18: 0 | I18: 1.2922688
A19: motor | B19: third_party_prop | C19: 44287 | D19: 14 | E19: 2006 | F19: 1 | G19: 1 | H19: 1 | I19: 1.0024406
A20: motor | B20: third_party_prop | C20: 44378 | D20: 13 | E20: 2083 | F20: 1 | G20: 1 | H20: 2 | I20: 1.0000369
A21: motor | B21: third_party_prop | C21: 44470 | D21: 12 | E21: 2264 | F21: 1 | G21: 1 | H21: 3 | I21: 1.0002773
A22: motor | B22: third_party_prop | C22: 44562 | D22: 11 | E22: 2080 | F22: 1 | G22: 1 | H22: 4 | I22: 1.0020811
A23: motor | B23: third_party_prop | C23: 44652 | D23: 10 | E23: 2178 | F23: 1 | G23: 1 | H23: 5 | I23: 1.0015696
A24: motor | B24: third_party_prop | C24: 44743 | D24: 9 | E24: 2227 | F24: 1 | G24: 1 | H24: 6 | I24: 1.0001581
A25: motor | B25: third_party_prop | C25: 44835 | D25: 8 | E25: 2316 | F25: 1 | G25: 1 | H25: 7 | I25: 1
A26: motor | B26: third_party_prop | C26: 44927 | D26: 7 | E26: 1995 | F26: 1 | G26: 1 | H26: 8 | I26: 1
A27: motor | B27: third_party_prop | C27: 45017 | D27: 6 | E27: 2086 | F27: 1.0001581 | G27: 0.9998419 | H27: 9 | I27: 1
A28: motor | B28: third_party_prop | C28: 45108 | D28: 5 | E28: 2088 | F28: 1.0017279 | G28: 0.99827504 | H28: 10 | I28: 1
A29: motor | B29: third_party_prop | C29: 45200 | D29: 4 | E29: 2188 | F29: 1.0038126 | G29: 0.99620187 | H29: 11 | I29: 1
... A32: motor | B32: third_party_prop | C32: 45474 | D32: 1 | E32: 2116 | F32: 1.0065786 | G32: 0.99346436 | H32: 14 | I32: 1
A33: motor | B33: third_party_prop | C33: 45566 | D33: 0 | E33: 1593 | F33: 1.3007702 | G33: 0.7687753 | H33: 15
A34: motor | B34: bodily_injury | C34: 44197 | D34: 15 | E34: 517 | F34: 1 | G34: 1 | H34: 0 | I34: 2.5033193
A35: motor | B35: bodily_injury | C35: 44287 | D35: 14 | E35: 500 | F35: 1.001938 | G35: 0.99806576 | H35: 1 | I35: 1.3725032
A36: motor | B36: bodily_injury | C36: 44378 | D36: 13 | E36: 556 | F36: 1.001938 | G36: 0.99806576 | H36: 2 | I36: 1.164342
A37: motor | B37: bodily_injury | C37: 44470 | D37: 12 | E37: 571 | F37: 1.0032143 | G37: 0.99679596 | H37: 3 | I37: 1.0837235
A38: motor | B38: bodily_injury | C38: 44562 | D38: 11 | E38: 495 | F38: 1.0050921 | G38: 0.99493366 | H38: 4 | I38: 1.0464151
A39: motor | B39: bodily_injury | C39: 44652 | D39: 10 | E39: 533 | F39: 1.0070051 | G39: 0.99304359 | H39: 5 | I39: 1.0305146
A40: motor | B40: bodily_injury | C40: 44743 | D40: 9 | E40: 540 | F40: 1.010202 | G40: 0.98990105 | H40: 6 | I40: 1.0148739
A41: motor | B41: bodily_injury | C41: 44835 | D41: 8 | E41: 573 | F41: 1.0143253 | G41: 0.98587706 | H41: 7 | I41: 1.0102259
A42: motor | B42: bodily_injury | C42: 44927 | D42: 7 | E42: 503 | F42: 1.0246977 | G42: 0.97589761 | H42: 8 | I42: 1.0040816
A43: motor | B43: bodily_injury | C43: 45017 | D43: 6 | E43: 528 | F43: 1.0399389 | G43: 0.96159494 | H43: 9 | I43: 1.0031746
A44: motor | B44: bodily_injury | C44: 45108 | D44: 5 | E44: 532 | F44: 1.0716722 | G44: 0.93312116 | H44: 10 | I44: 1.0019033
A45: motor | B45: bodily_injury | C45: 45200 | D45: 4 | E45: 486 | F45: 1.121414 | G45: 0.89173137 | H45: 11 | I45: 1.0018718
... A48: motor | B48: bodily_injury | C48: 45474 | D48: 1 | E48: 293 | F48: 1.9421305 | G48: 0.51489845 | H48: 14 | I48: 1.001938
A49: motor | B49: bodily_injury | C49: 45566 | D49: 0 | E49: 120 | F49: 4.8617728 | G49: 0.20568629 | H49: 15
A50: motor | B50: theft | C50: 44197 | D50: 15 | E50: 356 | F50: 1 | G50: 1 | H50: 0 | I50: 1.0643546
A51: motor | B51: theft | C51: 44287 | D51: 14 | E51: 363 | F51: 1 | G51: 1 | H51: 1 | I51: 1
A52: motor | B52: theft | C52: 44378 | D52: 13 | E52: 379 | F52: 1 | G52: 1 | H52: 2 | I52: 1
A53: motor | B53: theft | C53: 44470 | D53: 12 | E53: 381 | F53: 1 | G53: 1 | H53: 3 | I53: 1.0008694
A54: motor | B54: theft | C54: 44562 | D54: 11 | E54: 377 | F54: 1 | G54: 1 | H54: 4 | I54: 1.001656
A55: motor | B55: theft | C55: 44652 | D55: 10 | E55: 400 | F55: 1 | G55: 1 | H55: 5 | I55: 1.0010479
A56: motor | B56: theft | C56: 44743 | D56: 9 | E56: 378 | F56: 1 | G56: 1 | H56: 6 | I56: 1
A57: motor | B57: theft | C57: 44835 | D57: 8 | E57: 381 | F57: 1 | G57: 1 | H57: 7 | I57: 1
A58: motor | B58: theft | C58: 44927 | D58: 7 | E58: 370 | F58: 1 | G58: 1 | H58: 8 | I58: 1
A59: motor | B59: theft | C59: 45017 | D59: 6 | E59: 436 | F59: 1 | G59: 1 | H59: 9 | I59: 1
A60: motor | B60: theft | C60: 45108 | D60: 5 | E60: 417 | F60: 1.0010479 | G60: 0.99895315 | H60: 10 | I60: 1
A61: motor | B61: theft | C61: 45200 | D61: 4 | E61: 378 | F61: 1.0027057 | G61: 0.9973016 | H61: 11 | I61: 1
... A64: motor | B64: theft | C64: 45474 | D64: 1 | E64: 376 | F64: 1.0035774 | G64: 0.99643532 | H64: 14 | I64: 1
A65: motor | B65: theft | C65: 45566 | D65: 0 | E65: 365 | F65: 1.0681623 | G65: 0.93618736 | H65: 15
A66: motor | B66: glass_hail | C66: 44197 | D66: 15 | E66: 828 | F66: 1 | G66: 1 | H66: 0 | I66: 1.0885312
A67: motor | B67: glass_hail | C67: 44287 | D67: 14 | E67: 868 | F67: 1 | G67: 1 | H67: 1 | I67: 1
A68: motor | B68: glass_hail | C68: 44378 | D68: 13 | E68: 879 | F68: 1 | G68: 1 | H68: 2 | I68: 1
A69: motor | B69: glass_hail | C69: 44470 | D69: 12 | E69: 997 | F69: 1 | G69: 1 | H69: 3 | I69: 1.0006054
A70: motor | B70: glass_hail | C70: 44562 | D70: 11 | E70: 973 | F70: 1 | G70: 1 | H70: 4 | I70: 1.0034709
A71: motor | B71: glass_hail | C71: 44652 | D71: 10 | E71: 949 | F71: 1 | G71: 1 | H71: 5 | I71: 1.0018043
A72: motor | B72: glass_hail | C72: 44743 | D72: 9 | E72: 996 | F72: 1 | G72: 1 | H72: 6 | I72: 1
A73: motor | B73: glass_hail | C73: 44835 | D73: 8 | E73: 1021 | F73: 1 | G73: 1 | H73: 7 | I73: 1
A74: motor | B74: glass_hail | C74: 44927 | D74: 7 | E74: 929 | F74: 1 | G74: 1 | H74: 8 | I74: 1
A75: motor | B75: glass_hail | C75: 45017 | D75: 6 | E75: 999 | F75: 1 | G75: 1 | H75: 9 | I75: 1
A76: motor | B76: glass_hail | C76: 45108 | D76: 5 | E76: 986 | F76: 1.0018043 | G76: 0.99819896 | H76: 10 | I76: 1
A77: motor | B77: glass_hail | C77: 45200 | D77: 4 | E77: 1198 | F77: 1.0052814 | G77: 0.99474631 | H77: 11 | I77: 1
... A80: motor | B80: glass_hail | C80: 45474 | D80: 1 | E80: 1054 | F80: 1.00589 | G80: 0.99414448 | H80: 14 | I80: 1
A81: motor | B81: glass_hail | C81: 45566 | D81: 0 | E81: 976 | F81: 1.0949426 | G81: 0.91328984 | H81: 15
A82: buildings | B82: storm | C82: 44197 | D82: 15 | E82: 511 | F82: 1 | G82: 1 | H82: 0 | I82: 1.1404635
A83: buildings | B83: storm | C83: 44287 | D83: 14 | E83: 384 | F83: 1 | G83: 1 | H83: 1 | I83: 1.0002902
A84: buildings | B84: storm | C84: 44378 | D84: 13 | E84: 397 | F84: 1 | G84: 1 | H84: 2 | I84: 1
A85: buildings | B85: storm | C85: 44470 | D85: 12 | E85: 480 | F85: 1 | G85: 1 | H85: 3 | I85: 1.0001712
A86: buildings | B86: storm | C86: 44562 | D86: 11 | E86: 585 | F86: 1 | G86: 1 | H86: 4 | I86: 1.0029257
A87: buildings | B87: storm | C87: 44652 | D87: 10 | E87: 406 | F87: 1 | G87: 1 | H87: 5 | I87: 1.0023226
A88: buildings | B88: storm | C88: 44743 | D88: 9 | E88: 417 | F88: 1 | G88: 1 | H88: 6 | I88: 1
A89: buildings | B89: storm | C89: 44835 | D89: 8 | E89: 557 | F89: 1 | G89: 1 | H89: 7 | I89: 1
A90: buildings | B90: storm | C90: 44927 | D90: 7 | E90: 582 | F90: 1 | G90: 1 | H90: 8 | I90: 1
A91: buildings | B91: storm | C91: 45017 | D91: 6 | E91: 428 | F91: 1 | G91: 1 | H91: 9 | I91: 1
A92: buildings | B92: storm | C92: 45108 | D92: 5 | E92: 406 | F92: 1.0023226 | G92: 0.99768275 | H92: 10 | I92: 1
A93: buildings | B93: storm | C93: 45200 | D93: 4 | E93: 715 | F93: 1.0052551 | G93: 0.99477235 | H93: 11 | I93: 1
... A96: buildings | B96: storm | C96: 45474 | D96: 1 | E96: 391 | F96: 1.005719 | G96: 0.99431353 | H96: 14 | I96: 1
A97: buildings | B97: storm | C97: 45566 | D97: 0 | E97: 450 | F97: 1.1469858 | G97: 0.87185037 | H97: 15
A98: buildings | B98: flood | C98: 44197 | D98: 15 | E98: 130 | F98: 1 | G98: 1 | H98: 0 | I98: 1.1427796
A99: buildings | B99: flood | C99: 44287 | D99: 14 | E99: 130 | F99: 1 | G99: 1 | H99: 1 | I99: 1
A100: buildings | B100: flood | C100: 44378 | D100: 13 | E100: 158 | F100: 1 | G100: 1 | H100: 2 | I100: 1
A101: buildings | B101: flood | C101: 44470 | D101: 12 | E101: 136 | F101: 1 | G101: 1 | H101: 3 | I101: 1
A102: buildings | B102: flood | C102: 44562 | D102: 11 | E102: 134 | F102: 1 | G102: 1 | H102: 4 | I102: 1.0039012
A103: buildings | B103: flood | C103: 44652 | D103: 10 | E103: 145 | F103: 1 | G103: 1 | H103: 5 | I103: 1
A104: buildings | B104: flood | C104: 44743 | D104: 9 | E104: 160 | F104: 1 | G104: 1 | H104: 6 | I104: 1
A105: buildings | B105: flood | C105: 44835 | D105: 8 | E105: 146 | F105: 1 | G105: 1 | H105: 7 | I105: 1
A106: buildings | B106: flood | C106: 44927 | D106: 7 | E106: 126 | F106: 1 | G106: 1 | H106: 8 | I106: 1
A107: buildings | B107: flood | C107: 45017 | D107: 6 | E107: 134 | F107: 1 | G107: 1 | H107: 9 | I107: 1
A108: buildings | B108: flood | C108: 45108 | D108: 5 | E108: 145 | F108: 1 | G108: 1 | H108: 10 | I108: 1
A109: buildings | B109: flood | C109: 45200 | D109: 4 | E109: 145 | F109: 1.0039012 | G109: 0.99611399 | H109: 11 | I109: 1
... A112: buildings | B112: flood | C112: 45474 | D112: 1 | E112: 138 | F112: 1.0039012 | G112: 0.99611399 | H112: 14 | I112: 1
A113: buildings | B113: flood | C113: 45566 | D113: 0 | E113: 108 | F113: 1.1472378 | G113: 0.87165889 | H113: 15
A114: buildings | B114: escape_of_water | C114: 44197 | D114: 15 | E114: 736 | F114: 1 | G114: 1 | H114: 0 | I114: 1.1996442
...

Sheet Validation
A1: model | B1: basis | C1: line | D1: 2023 | E1: 2024 | F1: mean_2023_24
A2: SAM 3 (rerun) | B2: developed | C2: ALL | D2: 0.10639662 | E2: 0.10547752 | F2: 0.10593707
A3: SAM 3 (rerun) | B3: developed | C3: buildings | D3: 0.071028137 | E3: 0.073367901 | F3: 0.072198019
A4: SAM 3 (rerun) | B4: developed | C4: contents | D4: 0.070707766 | E4: 0.064050396 | F4: 0.067379081
A5: SAM 3 (rerun) | B5: developed | C5: motor | D5: 0.052966091 | E5: 0.055473012 | F5: 0.054219551
A6: SAM 3 (rerun) | B6: reported_adj | C6: ALL | D6: 0.10555561 | E6: 0.097321339 | F6: 0.10143847
A7: SAM 3 (rerun) | B7: reported_adj | C7: buildings | D7: 0.071185151 | E7: 0.074707973 | F7: 0.072946562
A8: SAM 3 (rerun) | B8: reported_adj | C8: contents | D8: 0.070717378 | E8: 0.063877359 | F8: 0.067297369
A9: SAM 3 (rerun) | B9: reported_adj | C9: motor | D9: 0.052498907 | E9: 0.044683323 | F9: 0.048591115
A10: SAM 3 (rerun) | B10: reported_raw | C10: ALL | D10: 0.10424088 | E10: 0.09846052 | F10: 0.1013507
A11: SAM 3 (rerun) | B11: reported_raw | C11: buildings | D11: 0.071185151 | E11: 0.074707973 | F11: 0.072946562
A12: SAM 3 (rerun) | B12: reported_raw | C12: contents | D12: 0.070717378 | E12: 0.063877359 | F12: 0.067297369
A13: SAM 3 (rerun) | B13: reported_raw | C13: motor | D13: 0.042819583 | E13: 0.046404857 | F13: 0.04461222
... A37: blend with SAM 3 (submitted form) | B37: reported_raw | C37: motor | D37: 0.045060508 | E37: 0.048891365 | F37: 0.046975936

Sheet Peril_Scores
A1: line | B1: peril | C1: method | D1: developed_2023 | E1: developed_2024 | F1: reported_adj_2023 | G1: reported_adj_2024 | H1: reported_raw_2023 | I1: reported_raw_2024
A2: buildings | B2: accidental_damage | C2: freq_sev | D2: 0.14401457 | E2: 0.13484867 | F2: 0.14400122 | G2: 0.13497064 | H2: 0.14400122 | I2: 0.13497064
A3: buildings | B3: accidental_damage | C3: tweedie | D3: 0.13891863 | E3: 0.12882909 | F3: 0.13890765 | G3: 0.12897735 | H3: 0.13890765 | I3: 0.12897735
A4: buildings | B4: escape_of_water | C4: freq_sev | D4: 0.034914442 | E4: 0.046944237 | F4: 0.034933122 | G4: 0.046786423 | H4: 0.034933122 | I4: 0.046786423
A5: buildings | B5: escape_of_water | C5: tweedie | D5: 0.029338924 | E5: 0.045788801 | F5: 0.029372252 | G5: 0.045695579 | H5: 0.029372252 | I5: 0.045695579
A6: buildings | B6: fire | C6: freq_sev | D6: 0.01560368 | E6: 0.031005298 | F6: 0.015602918 | G6: 0.031058989 | H6: 0.015602918 | I6: 0.031058989
A7: buildings | B7: fire | C7: tweedie | D7: 0.024728959 | E7: 0.027598788 | F7: 0.024732309 | G7: 0.027679161 | H7: 0.024732309 | I7: 0.027679161
A8: buildings | B8: flood | C8: freq_sev | D8: 0.4737148 | E8: 0.4380655 | F8: 0.47372596 | G8: 0.43800431 | H8: 0.47372596 | I8: 0.43800431
A9: buildings | B9: flood | C9: tweedie | D9: 0.45831376 | E9: 0.42866793 | F9: 0.45832917 | G9: 0.42871752 | H9: 0.45832917 | I9: 0.42871752
A10: buildings | B10: storm | C10: freq_sev | D10: 0.052248348 | E10: 0.063849071 | F10: 0.052281451 | G10: 0.063307295 | H10: 0.052281451 | I10: 0.063307295
A11: buildings | B11: storm | C11: tweedie | D11: 0.05201257 | E11: 0.064735913 | F11: 0.052040906 | G11: 0.064373736 | H11: 0.052040906 | I11: 0.064373736
A12: buildings | B12: subsidence | C12: freq_sev | D12: 0.066521427 | E12: 0.076107232 | F12: 0.066848932 | G12: 0.072714679 | H12: 0.066848932 | I12: 0.072714679
A13: buildings | B13: subsidence | C13: tweedie | D13: 0.062658334 | E13: 0.075572362 | F13: 0.06285887 | G13: 0.071118772 | H13: 0.06285887 | I13: 0.071118772
... A31: motor | B31: third_party_prop | C31: tweedie | D31: 0.059939797 | E31: 0.05096594 | F31: 0.059908212 | G31: 0.050809476 | H31: 0.059908212 | I31: 0.050809476

Sheet SAM3_Blend
A1: line | B1: weight_wendy07 | C1: weight_sam03 | D1: d2_wendy07 | E1: d2_sam03 | F1: d2_blend | G1: crossfold_gain_vs_wendy07 | H1: rule
A2: motor | B2: 0.8 | C2: 0.2 | D2: 0.046874343 | E2: 0.04461222 | F2: 0.046975936 | G2: 1e-04 / 1e-04 | H2: weight on grid 0.1 maximising mean 2023-24 reported_raw D2; cross-fold = chosen on one fold, scored on the other
A3: buildings | B3: 0.5 | C3: 0.5 | D3: 0.073298929 | E3: 0.072946562 | F3: 0.074169299 | G3: 0.00108 / 0.00038 | H3: weight on grid 0.1 maximising mean 2023-24 reported_raw D2; cross-fold = chosen on one fold, scored on the other
A4: contents | B4: 0.6 | C4: 0.4 | D4: 0.067893008 | E4: 0.067297369 | F4: 0.068597622 | G4: 0.00082 / 0.00051 | H4: weight on grid 0.1 maximising mean 2023-24 reported_raw D2; cross-fold = chosen on one fold, scored on the other

Sheet Forecast_2025
A1: level | B1: line | C1: peril | D1: method | E1: predicted_total | F1: predicted_burn
A2: peril (WENDY 7 part) | B2: motor | C2: own_damage | D2: freq_sev | E2: 22005599 | F2: 110.03703
A3: peril (WENDY 7 part) | B3: motor | C3: third_party_prop | D3: freq_sev | E3: 35888574 | F3: 179.4576
A4: peril (WENDY 7 part) | B4: motor | C4: bodily_injury | D4: tweedie | E4: 40056646 | F4: 200.29968
A5: peril (WENDY 7 part) | B5: motor | C5: theft | D5: freq_sev | E5: 9791964.9 | F5: 48.963844
A6: peril (WENDY 7 part) | B6: motor | C6: glass_hail | D6: freq_sev | E6: 4994094.7 | F6: 24.972524
A7: peril (WENDY 7 part) | B7: buildings | C7: storm | D7: freq_sev | E7: 9033794 | F7: 60.127525
A8: peril (WENDY 7 part) | B8: buildings | C8: flood | D8: freq_sev | E8: 19951488 | F8: 132.79399
A9: peril (WENDY 7 part) | B9: buildings | C9: escape_of_water | D9: freq_sev | E9: 18971445 | F9: 126.27098
A10: peril (WENDY 7 part) | B10: buildings | C10: subsidence | D10: freq_sev | E10: 9155904.9 | F10: 60.940276
A11: peril (WENDY 7 part) | B11: buildings | C11: fire | D11: freq_sev | E11: 14982751 | F11: 99.722853
A12: peril (WENDY 7 part) | B12: buildings | C12: accidental_damage | D12: freq_sev | E12: 1298444 | F12: 8.6422411
A13: peril (WENDY 7 part) | B13: contents | C13: theft | D13: freq_sev | E13: 8260076.6 | F13: 55.021777
... A19: line (WENDY 7 part) | B19: contents | C19: all | D19: - | E19: 18969425 | F19: 126.35857

Sheet Feature_Counts
A1: line | B1: peril | C1: freq_features | D1: sev_features | E1: all_features
A2: motor | B2: own_damage | C2: 38 | D2: 11 | E2: 39
A3: motor | B3: third_party_prop | C3: 31 | D3: 6 | E3: 31
A4: motor | B4: bodily_injury | C4: 18 | D4: 5 | E4: 19
A5: motor | B5: theft | C5: 21 | D5: 9 | E5: 21
A6: motor | B6: glass_hail | C6: 16 | D6: 9 | E6: 18
A7: buildings | B7: storm | C7: 17 | D7: 12 | E7: 22
A8: buildings | B8: flood | C8: 10 | D8: 11 | E8: 13
A9: buildings | B9: escape_of_water | C9: 28 | D9: 10 | E9: 31
A10: buildings | B10: subsidence | C10: 14 | D10: 12 | E10: 18
A11: buildings | B11: fire | C11: 20 | D11: 9 | E11: 24
A12: buildings | B12: accidental_damage | C12: 21 | D12: 5 | E12: 23
A13: contents | B13: theft | C13: 25 | D13: 9 | E13: 27
... A16: contents | B16: flood | C16: 13 | D16: 11 | E16: 16
